Workbook

Sheet Summary
A1: Intune Baseline — Policy to Security Framework Mapping
A2: Source: CIS_Compliance_Baseline_v2.xlsx (‘Compliance Baseline’ sheet), cross-referenced against the 222 policy files in source-pack/
A3: Every NIST / ISO value is copied verbatim from the workbook. Nothing is inferred: where the workbook has no data, the cells are left blank and the policy is marked UNMAPPED.
A5: COVERAGE
A6: Policies in the pack | B6: =COUNTA('Policy Mapping'!A2:A223) -> 222 | C6: One row per policy file.
A7: Mapped to a framework | B7: =COUNTIF('Policy Mapping'!N2:N223,"mapped") -> 198 | C7: Has a workbook row with NIST / ISO values.
A8: Unmapped | B8: =COUNTIF('Policy Mapping'!N2:N223,"<>mapped") -> 24 | C8: Workbook row is numbered but blank.
A9: Coverage % | B9: =IF(B6=0,0,B7/B6) -> 0.89189189 | C9: Mapped as a share of all policies.
A10: Distinct NIST controls | B10: =SUMPRODUCT(('Control Coverage'!A2:A48="NIST SP 800-53 Rev 5")*1) -> 31 | C10: Rev 5 controls cited at least once.
A11: Distinct ISO clauses | B11: =SUMPRODUCT(('Control Coverage'!A2:A48="ISO/IEC 27001:2022")*1) -> 16 | C11: 27001:2022 Annex A clauses cited.
A13: HOW EACH MAPPING WAS MATCHED
A14: Every mapping is traceable. ‘match_method’ on the Policy Mapping tab records how the workbook row was tied to the policy file, so any row can be spot-checked.
A15: Match method | B15: Policies | C15: What it means
A16: exact | B16: =COUNTIF('Policy Mapping'!O2:O223,"exact") -> 164 | C16: Workbook policy name equals the filename, character for character.
A17: punctuation | B17: =COUNTIF('Policy Mapping'!O2:O223,"punctuation") -> 14 | C17: Matched after normalising punctuation, .mobileconfig, export timestamps, or a mangled curly apostrophe (#U2019).
A18: whitespace | B18: =COUNTIF('Policy Mapping'!O2:O223,"whitespace") -> 10 | C18: Matched after collapsing double spaces and trimming.
A19: prefix | B19: =COUNTIF('Policy Mapping'!O2:O223,"prefix") -> 10 | C19: Matched after normalising a differing rule-name prefix, e.g. workbook “ASR - BLOCK - Block X” vs file “CISv4 - WIN - L1 - ASR: Block X”.
A20: unmapped | B20: =COUNTIF('Policy Mapping'!O2:O223,"unmapped") -> 24 | C20: No workbook row exists for this policy — the row is numbered but entirely blank.
A23: KNOWN ISSUES IN THE SOURCE WORKBOOK
A24: • 24 rows are numbered but completely blank — the workbook presents itself as 222 policies but documents 198. These cannot be mapped from anything in the pack; the workbook has to be filled in. See the ‘Unmapped Gap’ tab.
A25: • 15 rows record a literal “-” instead of a control. All are Edge CIS items, mostly browser-UX controls with no clean framework analogue. They appear as “(none recorded)” on the Policy x Control tab.
A26: • One level disagreement: “Configure the list of types that are excluded from synchronization” is L2 in the workbook but L1 in the filename. This workbook reports the workbook’s value (L2).
A27: • 34 policies were only matched after normalising naming drift between the workbook and the exported filenames (double spaces, prefixes, punctuation). Their mappings are the workbook’s own — see match_method.

Sheet Operational Impact
A1: Operational impact — effect on operations and end-user experience
A2: Scoped to a typical client profile: CAD engineers, a small dev team, majority general office staff, 200+ endpoints. Every row states what this pack ACTUALLY configures, what the user experiences, and how the service desk should handle it. The Service Desk Brief tab is the same information filtered to the handover sheet — both tabs are generated from one source, so they cannot drift apart.
A4: Policy | B4: Configured as | C4: Who it hits | D4: Assessed severity | E4: What actually breaks | F4: What the user reports | G4: Service desk handling | H4: What the service desk should do | I4: When it bites | J4: Mitigation | K4: Evidence / provenance
A5: CISv3 - EDGE - L2 - Allow file selection dialogs | B5: AllowFileSelectionDialogs = 0 (blocked) | C5: All users · Office | D5: HIGH | E5: File selection dialogs are blocked in Edge. Users cannot browse to pick a file — no attaching to webmail, no uploading a drawing to a client portal, no 'Upload' in SharePoint/Teams web, no attaching to a support ticket. Save-as dialogs are affected too. | F5: “I can't attach a file / the Upload button does nothing” | G5: Expected | H5: Not a fault and there is no client-side fix. Escalate — this is an L2 scoping decision. | I5: First time anyone tries to upload or attach anything in the browser. Immediate and constant. | J5: This is an L2 control. For an office-heavy fleet, scope the Edge L2 set out entirely or exclude this single policy. Test the customer's actual web apps — portals, ticketing, cloud CAD — first. | K5: Setting verified + Microsoft Edge policy docs
A6: CISv3 - EDGE - L2 - Allow or block audio capture | B6: AudioCaptureAllowed = 0 (microphone blocked) | C6: All users | D6: HIGH | E6: Websites cannot access the microphone. Browser-based Teams, Zoom, Google Meet and Webex calls have no audio. Web dictation and voice tools stop working. | F6: “I have no microphone in the Teams/Zoom web app” | G6: Expected | H6: Move the user to the desktop client. Escalate if browser calls are a business requirement. | I6: First browser-based call after apply. | J6: Survivable if the customer uses desktop clients exclusively; not if anyone joins calls in a browser (guests, contractors, BYOD). Confirm before deploying. L2 — scope out with the rest if unsure. | K6: Setting verified + Microsoft Edge policy docs
A7: CISv3 - EDGE - L2 - Allow or deny screen capture | B7: ScreenCaptureAllowed = 0 (blocked) | C7: All users · Service desk | D7: HIGH | E7: Sites cannot capture the screen. Screen sharing in browser-based Teams/Zoom/Meet fails, and browser-delivered remote support tools cannot show or take the screen. | F7: “I can't share my screen in a browser meeting” | G7: Expected | H7: Use the desktop client. If your own remote-support tool is browser-based, escalate urgently. | I7: First time someone tries to share their screen from a browser. | J7: Check how the service desk actually does remote support — if it is browser-delivered, this breaks their own tooling. L2, scope out if so. | K7: Setting verified + Microsoft Edge policy docs
A8: Network security: LAN Manager auth level + SMBv1 disabled + SMB signing always | B8: LmCompatibilityLevel = 5 (NTLMv2 only, refuse LM & NTLM) · SMBv1 client driver = 4 (disabled) · SMBv1 server = 0 · client and server digital signing = 1 (always) | C8: CAD · Office · Service desk | D8: HIGH | E8: Legacy network kit that cannot do NTLMv2, SMBv2+ or SMB signing stops authenticating. In an engineering or architecture firm that typically means the office MFP's scan-to-folder stops working, older NAS boxes become unreachable, and network plotters or scanners with old firmware drop off. SMB signing also adds CPU cost to large transfers — noticeable opening big CAD assemblies from a file server. | F8: “The photocopier can't scan to my folder any more” | G8: Investigate | H8: Check the device's firmware and SMB/auth capability. A firmware update usually fixes it — do not weaken the policy per-device. | I8: Immediately for authentication; file-open slowdowns show up under load. | J8: Inventory the network kit BEFORE deploying: every MFP, scanner, plotter and NAS. Firmware updates fix most of it. This is the classic 'security baseline broke the photocopier' scenario and it is very likely in this client profile. | K8: Settings verified + Microsoft LAN Manager authentication level docs. MFP/NAS impact is assessment — inventory to confirm.
F9: “Opening drawings from the server got slow” | G9: Investigate | H9: Confirm it correlates with the rollout. Escalate with timings — this is a tuning decision, not a device fault.
A10: Windows Hello for Business — Require Security Device + Exclude TPM 1.2 + Disable Post Logon Provisioning + Multi-Factor Unlock | B10: RequireSecurityDevice = True · ExcludeSecurityDevices/TPM12 = True · DisablePostLogonProvisioning = True · Multi-factor unlock: group A = face/fingerprint, group B = PIN/face/fingerprint, plus a bluetooth proximity signal at rssiMin -10 | C10: CAD (desktop towers) · All users | D10: HIGH | E10: Two compounding problems. (1) A device without TPM 2.0 will not provision Hello, and because post-logon provisioning is disabled the user is never prompted again — they silently stay on passwords and nobody notices the passwordless project didn't land. (2) Multi-factor unlock needs a group A factor, which is face or fingerprint. Desktop CAD workstations typically have neither, so those users may not be able to use Hello at all. The bluetooth signal at rssiMin -10 also needs the phone very close to register. | F10: “Windows Hello never asked me to set up / won't work on my desktop PC” | G10: Investigate | H10: Check TPM version and whether the device has a camera or fingerprint reader. Escalate — a fleet hardware question, not a per-user fix. | I10: At enrolment. Silent — this fails quietly rather than erroring. | J10: Audit TPM version across the fleet first. Decide explicitly whether desktop towers get biometric hardware or are excluded from multi-factor unlock. Loosen rssiMin if bluetooth proximity is used at all. | K10: Settings verified across 5 policies (4 are legacy OMA-URI) + Workbook note #22. Desktop-tower biometric gap is assessment.
A11: Baseline - Configure Windows protected print | B11: Protected Print Mode = Enabled (1) | C11: CAD · Office · Service desk | D11: HIGH | E11: Disables ALL third-party v3/v4 print drivers. Only Mopria-certified IPP printers work. Large-format plotters (DesignJet, imagePROGRAF, Océ) and MFP finishing — stapling, booklet, secure/PIN release — stop working. Legacy port monitors and DLL-based print utilities stop working. | F11: “I can't add the plotter / my printer driver won't install” | G11: Expected | H11: Check the printer against the Mopria certified list. If not certified it needs a policy exclusion — escalate, do not rebuild the machine. | I11: First print job after apply. Immediate and fleet-wide. | J11: Inventory printers against the Mopria certified list BEFORE deploying. If any plotter or MFP is not certified, exclude this policy or scope it to office devices only. Reversible — you can revert to driver-based printing. | K11: Setting verified + Microsoft 'Windows protected print mode for enterprises' docs
F12: “Stapling / booklet / secure PIN release has disappeared from the print dialog” | G12: Expected | H12: Escalate as a scoping decision. There is no client-side fix.
A13: CISv4 - WIN - L1 - UAC: Behavior of the elevation prompt for standard users | B13: ConsentPromptBehaviorUser = 0 (automatically deny) | C13: All users · Service desk | D13: HIGH | E13: Standard users get NO elevation prompt — the operation returns 'Access denied' and fails. A user cannot be talked through entering admin credentials because no prompt appears. Any install, driver update or self-elevating app just fails. | F13: “Nothing happens when I try to install something — it just says access denied” | G13: Expected | H13: Do not try to talk the user through a prompt — there isn't one. Use LAPS / admin-by-request / RMM elevation. | I13: Any time a non-admin hits something needing elevation. Constant. | J13: Ensure the service desk has a working elevation path first — LAPS, admin-by-request, or RMM elevation. Brief them that 'access denied with no prompt' is expected, not a broken machine. | K13: Setting verified + Microsoft UAC policy docs
A14: CISv4 - WIN - L1 - Credential Guard | B14: LsaCfgFlags = 1 (Enabled WITH UEFI lock) | C14: Dev team · Service desk | D14: HIGH | E14: Credential Guard with UEFI lock CANNOT be turned off remotely. If it breaks a developer's VM (VMware without nested virtualisation) or fails on incompatible hardware, the fix needs physical firmware access — a site visit per affected device across 200 endpoints. | F14: “My VM won't start / VMware says it can't run” | G14: Escalate immediately | H14: Escalate — needs a physical firmware change. Flag early: every affected machine is a site visit. | I14: At next reboot. Hardware/VM incompatibility shows immediately. | J14: Use LsaCfgFlags = 2 (enabled WITHOUT lock) for pilot so it stays remotely reversible; move to 1 only once proven. Verify TPM 2.0 + UEFI + 64-bit, and test dev machines running VMware/Hyper-V specifically. | K14: Setting verified + Microsoft DeviceGuard CSP docs. NOTE: the source workbook does NOT flag this — its note #8 covers LSA protection's UEFI lock only.
A15: Baseline - Device Control | B15: RemovableDiskDenyWriteAccess = 1 · AllowDirectMemoryAccess = 0 · AllowBluetooth = 2 | C15: CAD · Office · Service desk | D15: HIGH | E15: Writing to USB storage is denied — blocks 'copy the drawing set to a stick for site or the client'. DMA blocking can affect Thunderbolt docks and eGPU enclosures used on CAD workstations. | F15: “I can't save to my USB stick” | G15: Expected | H15: Point the user to the agreed alternative (OneDrive/SharePoint). Do not disable per-device. | I15: First attempt to save to USB. Very visible. | J15: Agree the file-transfer alternative with the customer BEFORE deploying. Pilot on a real CAD workstation with its actual dock. | K15: Settings verified + Workbook note #17. Dock/eGPU impact is assessment — test on real hardware.
F16: “My dock / second monitor stopped working” | G16: Investigate | H16: Confirm whether the dock is Thunderbolt/DMA-based. Test on an unenrolled machine before assuming hardware failure.
A17: Edge + Chrome extension allow-lists | B17: Default-deny allow-list (customer extension IDs required) | C17: All users | D17: HIGH | E17: Deployed unconfigured, ALL browser extensions are blocked — corporate VPN clients, password managers (Keeper), accessibility tools and screen readers included. | F17: “All my browser extensions vanished” | G17: Expected | H17: Collect the extension ID and escalate for the approved list. Do not sideload. | I17: Immediately on apply. | J17: Populate EdgeApprovedExtensionIds / ChromeApprovedExtensionIds before deploying. Survey what users actually have — 200 users will have a long tail nobody documented. | K17: Workbook notes #14 and #21 (both HIGH)
A18: CISv3 - EDGE - L2 - Allow users to proceed from the HTTPS warning page | B18: SSLErrorOverrideAllowed = 0 | C18: CAD · Service desk | D18: MEDIUM | E18: Users cannot click through a certificate warning. Internal kit with self-signed or expired certs becomes unreachable in Edge: NAS admin pages, printer and plotter web UIs, CAD licence server consoles, older intranet appliances. | F18: “I can't open the NAS / printer / licence server web page — the cert error won't let me through” | G18: Expected | H18: Install a proper certificate on the device, or escalate for an exclusion. Do not tell users to switch browser. | I18: First time someone opens an internal device's web page. | J18: Inventory internal HTTPS endpoints with self-signed certs and either install proper certs or exclude this policy. The service desk hits this constantly. | K18: Setting verified + Microsoft Edge policy docs. Internal-kit impact is assessment.
A19: Baseline - Microsoft Defender Antivirus (cloud block level + local admin merge + network file scanning) | B19: CloudBlockLevel = 6 (High Plus) · DisableLocalAdminMerge = 1 · AllowScanningNetworkFiles = 1 · PUAProtection = 1 · AvgCPULoadFactor = 30 | C19: CAD · Dev team | D19: MEDIUM | E19: High Plus cloud blocking is aggressive and flags rare or unsigned software — exactly what niche CAD plugins, licence managers and in-house dev tools look like. Local admins cannot add their own Defender exclusions, so every false positive becomes a ticket. Real-time scanning of network files adds latency opening large CAD assemblies from a file server. | F19: “Defender quarantined our CAD plugin / licence manager” | G19: Investigate | H19: Do not ask the user to add an exclusion — they can't. Collect the file path and hash and escalate for a central exclusion. | I19: False positives cluster in the first 2-4 weeks; file-open latency is immediate under load. | J19: Pre-stage exclusions for the CAD suite and licence manager before deploying. Monitor Defender alerts closely in the pilot. Have a fast central path to add exclusions, since users and local admins can no longer self-serve. | K19: Settings verified + Workbook notes #9 and #10. CAD plugin false-positive risk is assessment.
A20: CISv4 - WIN - L1 - Configure Lsa Protected Process (Enabled with UEFI Lock) | B20: ConfigureLsaProtectedProcess = 1 (UEFI lock) | C20: Service desk | D20: MEDIUM | E20: Same reversal problem as Credential Guard — undoing it needs BIOS-level intervention. Also blocks tools that inject into LSASS (some SSO agents, older RMM credential helpers). | F20: “Our SSO agent / credential helper stopped working after a reboot” | G20: Investigate | H20: Check whether the tool injects into LSASS. Escalate — reversing this needs BIOS access. | I20: At reboot; tool incompatibility surfaces within days. | J20: Deploy without UEFI lock first, confirm no tooling breaks, then lock. Agree BIOS access methodology before broad deployment. | K20: Setting verified + Workbook note #8
A21: CISv4 - WIN - L1 - ASR: Block untrusted and unsigned processes that run from USB | B21: Set to BLOCK — the only ASR rule shipping in block mode | C21: CAD · Service desk | D21: MEDIUM | E21: Unsigned executables run from removable media are blocked. Hits CAD licence dongles that ship an unsigned helper, vendor utilities run from USB, and portable diagnostic tools the service desk carries on a stick. | F21: “My CAD licence dongle stopped working” | G21: Investigate | H21: Check Defender logs for an ASR block event. If confirmed it needs an ASR exclusion — escalate. | I21: First time someone runs a tool from USB. | J21: Confirm whether any CAD licensing uses a USB dongle with an unsigned component. Keep service desk tooling on a network share or signed media. | K21: Setting verified. CAD dongle impact is assessment — verify against this customer's licensing.
A22: CISv4 - WIN - L1 - Allow Basic authentication (WinRM Client) | B22: Client = 0 (Basic auth disabled) | C22: Service desk | D22: MEDIUM | E22: Remote management tools using WinRM with username/password basic auth stop working. Kerberos and certificate auth still work. | F22: “Our remote support tool can't connect to this machine” | G22: Expected | H22: Confirm the tool's auth method. Migrating to Kerberos is the fix, not a per-device exception. | I22: Next time the RMM or a script connects. | J22: Identify RMM/automation using WinRM basic auth and migrate to Kerberos before deploying. Most likely policy to break the service desk's own tooling. | K22: Setting verified + Workbook note #12
A23: Edge: password manager disabled + sync disabled + import disabled | B23: PasswordManagerEnabled = 0 · SyncDisabled = 1 · ImportSavedPasswords / autofill / browser settings all = 0 | C23: Office · Service desk | D23: MEDIUM | E23: Edge will not save or autofill passwords, will not sync favourites and settings between a user's devices, and cannot import from another browser. For users with no corporate password manager this is a large day-one behaviour change and a password-reset ticket spike. | F23: “Edge won't save my passwords and my favourites didn't follow me” | G23: Expected | H23: Direct the user to the corporate password manager. Favourites must be exported manually before a rebuild. | I23: Immediately, and heavily during onboarding or machine refresh. | J23: Deploy a password manager (Keeper is already in this customer's approved extension list) and communicate it BEFORE these land. Sequence after any browser migration. | K23: Settings verified. Ticket-spike expectation is assessment.
F24: “I can't import my passwords into Edge” | G24: Expected | H24: Direct the user to the corporate password manager.
A25: Edge: IE mode reload blocked · ClickOnce blocked · DirectInvoke blocked | B25: InternetExplorerIntegrationReloadInIEModeAllowed = 0 · ClickOnceEnabled = 0 · DirectInvokeEnabled = 0 | C25: CAD · Office | D25: MEDIUM | E25: Legacy line-of-business web apps break. ClickOnce is still how a number of engineering and ERP vendors deploy their client; DirectInvoke is how some document systems open files directly. Users also cannot reload an unlisted site in IE mode. | F25: “Our ERP / document system won't launch from the browser” | G25: Investigate | H25: Identify how the app launches and escalate to add the site to the IE mode list or exclude the policy. | I25: When someone opens the affected app. | J25: Ask the customer what legacy web apps exist — engineering firms commonly have one ERP or document management system that needs one of these. Add sites to the IE mode list rather than leaving users to self-serve. | K25: Settings verified. Legacy app impact is assessment — confirm the app inventory.
A26: Baseline - Bitlocker Policy (BitLocker To Go) | B26: Unencrypted USB drives become read-only | C26: All users | D26: MEDIUM | E26: Users are prompted to encrypt a USB drive before writing. Intended, but reads as 'my USB stick is broken'. Compounds with Device Control above, which denies USB writes outright. | F26: “My USB stick has gone read-only” | G26: Expected | H26: Expected — the drive needs BitLocker encryption before it can be written to. | I26: First write to an unencrypted stick. | J26: Brief end users and the service desk before deploying. | K26: Workbook note #3 (INFO — intended behaviour)
A27: Baseline - Windows AI - Turn Off Copilot in Windows (User) | B27: TurnOffWindowsCopilot = 1 (user scope) · Click To Do disabled · Edge GenAI local model off · Recall blocked | C27: Office | D27: MEDIUM | E27: Copilot in Windows is removed for users. If the customer is paying for M365 Copilot or has staff already using it, this is a visible and unpopular removal that will be read as a fault. | F27: “Copilot has disappeared” | G27: Expected | H27: If the customer pays for M365 Copilot, escalate — likely a scoping error rather than an intended control. | I27: Immediately. | J27: Confirm the customer's AI position and licensing BEFORE deploying category 10. This is a business decision, not a security default — if they've bought Copilot, exclude this policy. | K27: Settings verified. Licensing conflict is assessment — ask the customer.
A28: Baseline - Windows Security Experience | B28: disablevirusui = 1 · disablenetworkui = 1 · disabledevicesecurityui = 1 · disableaccountprotectionui = 1 · disableappbrowserui = 1 · disablehealthui = 1 · disablefamilyui = 1 · hideransomwaredatarecovery = 1 · hidewindowssecuritynotificationareacontrol = 1 · disableenhancednotifications = 1 | C28: All users · Service desk | D28: MEDIUM | E28: Nearly every page of the Windows Security app is hidden — virus and threat protection, firewall and network protection, device security, account protection, app and browser control, and device health. The system tray icon is hidden too. Users cannot see whether protection is on, run a manual scan, view a detection, or release a file from quarantine. Critically, the service desk loses a standard triage step: they can no longer ask a user to open Windows Security and read out what it says. | F28: “Windows Security is empty / I can't tell if my antivirus is working” | G28: Expected | H28: Expected — the UI is hidden by policy, protection is still running. Confirm state from the Defender portal, not the endpoint. | I28: Immediately. Noticed the first time anyone tries to check their own protection status or the desk tries to triage a Defender issue. | J28: Make sure the desk triages Defender from the Defender portal or via the RMM instead of the local UI, and knows the local UI is intentionally empty. If the customer's users are expected to self-serve any Defender interaction at all, this needs scoping out. | K28: Settings verified. Service desk triage impact is assessment.
F29: “I can't run a virus scan / release a file from quarantine” | G29: Expected | H29: The user cannot do this themselves. Action it centrally from the Defender portal.
A30: ASR - Enable Controlled Folder Access (AUDIT mode) | B30: EnableControlledFolderAccess = 2 (audit) | C30: CAD · Office · Service desk | D30: LOW | E30: Blocks nothing — but still raises user-visible Defender notifications when an app writes to a protected folder. Users report these as 'a virus warning', so the policy costs ticket volume while providing logging only. CAD autosave and backup agents are the usual triggers. | F30: “Defender is warning about a file in my Documents folder” | G30: Expected — not blocking | H30: Reassure the user nothing was blocked. Log it — these events are the evidence for deciding whether block mode is safe. | I30: Continuously, wherever apps write to Documents or Desktop. | J30: Brief the desk that these are audit events, not blocks. Treat the volume as free intelligence — it is exactly the evidence needed to decide whether block mode would ever be safe here. | K30: Setting verified + Workbook note #5. Ticket-volume effect is assessment.
A31: CISv4 - WIN - L1 - Interactive logon: Machine inactivity limit | B31: MachineInactivityLimit = 900 seconds (15 minutes) | C31: CAD · Office | D31: LOW | E31: Screen locks after 15 minutes idle. CAD engineers watching a long render, plot or simulation will lock repeatedly while monitoring a job that needs no input. | F31: “My screen keeps locking while I'm watching a render” | G31: Expected | H31: Expected. Escalate only if there is a business case for a longer limit on CAD workstations. | I31: Constant, low-grade. | J31: Usually acceptable and hard to argue against with an auditor. Mention it in user comms so it isn't reported as a fault. | K31: Setting verified. CAD render impact is assessment.
A32: CISv4 - WIN - L2 - RDS idle session time limit | B32: IdleLimit = 900000 ms (15 minutes) | C32: Office · Service desk | D32: LOW | E32: Idle remote sessions disconnect after 15 minutes — awkward where staff RDP into a shared workstation or licence-server box and leave a long job running. | F32: “My remote session keeps dropping” | G32: Expected | H32: If someone relies on long unattended sessions, escalate as a scoping decision. | I32: Any idle remote session. | J32: Confirm nobody relies on long-running unattended remote sessions (CAD rendering, batch plotting on a shared box). | K32: Setting verified. Rendering/batch impact is assessment.
A33: Edge minor UX set: InPrivate off · Google Cast off · background apps off · profile creation off | B33: InPrivateModeAvailability = 1 (disabled) · EnableMediaRouter = 0 · BackgroundModeEnabled = 0 · BrowserAddProfileEnabled = 0 | C33: Office · Dev team | D33: LOW | E33: No InPrivate windows (devs use these to test as an anonymous user), no Google Cast to meeting-room screens, no second browser profile for a personal or client-tenant login. | F33: “I can't open an InPrivate window / cast to the meeting room screen” | G33: Expected | H33: Expected. Escalate only if meeting rooms depend on Cast. | I33: Ad hoc. | J33: Generally acceptable. Check whether meeting rooms rely on Cast, and whether anyone legitimately needs a second Edge profile for a client tenant. | K33: Settings verified. Use-case impact is assessment.
A35: VERIFIED SAFE — will not cause problems, despite what the source workbook's warnings imply
A36: Worth knowing so you don't over-scope the pilot or talk a customer out of controls they can safely have. Several policies the workbook rates HIGH risk ship in AUDIT mode in this pack, so they log without blocking.
A37: Policy | B37: Configured as | C37: Why it is safe as shipped | D37: Evidence
A38: ASR - Block process creations from PSExec and WMI | B38: Set to AUDIT | C38: Will NOT break RMM tooling or service desk scripts, despite the workbook rating it MEDIUM risk. | D38: Setting verified · workbook note #6
A39: ASR - Block execution of potentially obfuscated scripts | B39: Set to AUDIT | C39: Will NOT block developer build scripts, minified or packed JavaScript, or installer scripts. | D39: Setting verified
A40: ASR - Block all Office applications from creating child processes | B40: Set to AUDIT | C40: Will NOT break Office macros, add-ins or Office automation, despite the workbook rating it HIGH. | D40: Setting verified · workbook note #4
A41: Baseline - Windows Subsystem For Linux | B41: AllowWSL = 1 (permitted) | C41: WSL2 remains available to the dev team. Only WSL1 is blocked (AllowWSL1 = 0), which is rarely used. Kernel, networking, nested virtualisation and debug shell all remain user-configurable. | D41: Setting verified
A42: CISv3 - EDGE - L1 - Clear browsing data when Edge closes | B42: ClearBrowsingDataOnExit = 0 (disabled) | C42: Users will NOT be signed out of web apps every time Edge closes. The workbook's note #19 warns about this behaviour, but the policy as shipped does not enable it. | D42: Setting verified · contradicts workbook note #19
A43: CISv3 - EDGE - L1 - Allow download restrictions | B43: DownloadRestrictions = 4 (block malicious only) | C43: Downloads are NOT blocked wholesale — value 4 blocks malicious downloads only. Value 3 would have blocked everything; this is the safe setting. | D43: Setting verified + Microsoft DownloadRestrictions docs
A44: Defender - full scan on mapped network drives | B44: AllowFullScanOnMappedNetworkDrives = 0 | C44: Scheduled full scans will NOT traverse mapped drives, so a full scan won't hammer the CAD file server. (Real-time scanning of network files IS on — see the Defender row above.) | D44: Setting verified
A46: SEPARATE ISSUE — a per-customer value with no config slot
A47: Policy | B47: Configured as | C47: Why it matters | D47: Gap
A48: Local administrator rights — not managed by this baseline at all | B48: No LocalUsersAndGroups / restricted-groups policy anywhere in the 222 | C48: This baseline's effectiveness rests on users being standard users, but it never enforces that. UAC auto-deny, Device Control, ASR and the Defender settings are all far weaker against a local admin — and Defender exclusions are already locked to central management (DisableLocalAdminMerge = 1), which only makes sense if admin rights are rare. If the customer's CAD engineers or developers hold local admin (common, because their tooling historically demanded it), a large share of this baseline is advisory rather than enforced. | D48: Settle local admin scope explicitly at the start of the engagement, and manage it with LAPS or an admin-by-request tool. It is not in customer.config.psd1 and not in the pack — it is an assumption the pack silently depends on.
A49: Baseline - MDE Device Tag / Windows-Server-Defender-Device-Tag | B49: DeviceTagging/Group = "Intune MWP" — hardcoded | C49: Every customer gets the same Defender device tag, 'Intune MWP'. Device tags drive scoping, filtering and reporting in Defender, so a shared literal across all your customers is unhelpful at best and confusing in a multi-tenant MSSP view. | D49: Not in customer.config.psd1 — a per-customer value with no config slot, unlike EntraTenantId or the extension lists.

Sheet Service Desk Brief
A1: Service desk brief — expected calls after this baseline lands
A2: Hand this to the service desk before the pilot. Every row also appears on the Operational Impact tab against the policy that causes it — same source, so the two cannot disagree. Prevents the classic failure: a correctly-hardened endpoint gets rebuilt because nobody knew the control was intentional.
A4: User reports | B4: Caused by | C4: Expected or fault? | D4: Severity | E4: Why it happens | F4: What the service desk should do
A5: “I can't attach a file / the Upload button does nothing” | B5: CISv3 - EDGE - L2 - Allow file selection dialogs | C5: Expected | D5: HIGH | E5: File selection dialogs are blocked in Edge. Users cannot browse to pick a file — no attaching to webmail, no uploading a drawing to a client portal, no 'Upload' in SharePoint/Teams web, no attaching to a support ticket. Save-as dialogs are affected too. | F5: Not a fault and there is no client-side fix. Escalate — this is an L2 scoping decision.
A6: “I have no microphone in the Teams/Zoom web app” | B6: CISv3 - EDGE - L2 - Allow or block audio capture | C6: Expected | D6: HIGH | E6: Websites cannot access the microphone. Browser-based Teams, Zoom, Google Meet and Webex calls have no audio. Web dictation and voice tools stop working. | F6: Move the user to the desktop client. Escalate if browser calls are a business requirement.
A7: “I can't share my screen in a browser meeting” | B7: CISv3 - EDGE - L2 - Allow or deny screen capture | C7: Expected | D7: HIGH | E7: Sites cannot capture the screen. Screen sharing in browser-based Teams/Zoom/Meet fails, and browser-delivered remote support tools cannot show or take the screen. | F7: Use the desktop client. If your own remote-support tool is browser-based, escalate urgently.
A8: “The photocopier can't scan to my folder any more” | B8: Network security: LAN Manager auth level + SMBv1 disabled + SMB signing always | C8: Investigate | D8: HIGH | E8: Legacy network kit that cannot do NTLMv2, SMBv2+ or SMB signing stops authenticating. In an engineering or architecture firm that typically means the office MFP's scan-to-folder stops working, older NAS boxes become unreachable, and network plotters or scanners with old firmware drop off. SMB signin | F8: Check the device's firmware and SMB/auth capability. A firmware update usually fixes it — do not weaken the policy per-device.
A9: “Opening drawings from the server got slow” | B9: Network security: LAN Manager auth level + SMBv1 disabled + SMB signing always | C9: Investigate | D9: HIGH | E9: Legacy network kit that cannot do NTLMv2, SMBv2+ or SMB signing stops authenticating. In an engineering or architecture firm that typically means the office MFP's scan-to-folder stops working, older NAS boxes become unreachable, and network plotters or scanners with old firmware drop off. SMB signin | F9: Confirm it correlates with the rollout. Escalate with timings — this is a tuning decision, not a device fault.
A10: “Windows Hello never asked me to set up / won't work on my desktop PC” | B10: Windows Hello for Business — Require Security Device + Exclude TPM 1.2 + Disable Post Logon Provisioning + Multi-Factor Unlock | C10: Investigate | D10: HIGH | E10: Two compounding problems. (1) A device without TPM 2.0 will not provision Hello, and because post-logon provisioning is disabled the user is never prompted again — they silently stay on passwords and nobody notices the passwordless project didn't land. (2) Multi-factor unlock needs a group A factor, | F10: Check TPM version and whether the device has a camera or fingerprint reader. Escalate — a fleet hardware question, not a per-user fix.
A11: “I can't add the plotter / my printer driver won't install” | B11: Baseline - Configure Windows protected print | C11: Expected | D11: HIGH | E11: Disables ALL third-party v3/v4 print drivers. Only Mopria-certified IPP printers work. Large-format plotters (DesignJet, imagePROGRAF, Océ) and MFP finishing — stapling, booklet, secure/PIN release — stop working. Legacy port monitors and DLL-based print utilities stop working. | F11: Check the printer against the Mopria certified list. If not certified it needs a policy exclusion — escalate, do not rebuild the machine.
A12: “Stapling / booklet / secure PIN release has disappeared from the print dialog” | B12: Baseline - Configure Windows protected print | C12: Expected | D12: HIGH | E12: Disables ALL third-party v3/v4 print drivers. Only Mopria-certified IPP printers work. Large-format plotters (DesignJet, imagePROGRAF, Océ) and MFP finishing — stapling, booklet, secure/PIN release — stop working. Legacy port monitors and DLL-based print utilities stop working. | F12: Escalate as a scoping decision. There is no client-side fix.
A13: “Nothing happens when I try to install something — it just says access denied” | B13: CISv4 - WIN - L1 - UAC: Behavior of the elevation prompt for standard users | C13: Expected | D13: HIGH | E13: Standard users get NO elevation prompt — the operation returns 'Access denied' and fails. A user cannot be talked through entering admin credentials because no prompt appears. Any install, driver update or self-elevating app just fails. | F13: Do not try to talk the user through a prompt — there isn't one. Use LAPS / admin-by-request / RMM elevation.
A14: “My VM won't start / VMware says it can't run” | B14: CISv4 - WIN - L1 - Credential Guard | C14: Escalate immediately | D14: HIGH | E14: Credential Guard with UEFI lock CANNOT be turned off remotely. If it breaks a developer's VM (VMware without nested virtualisation) or fails on incompatible hardware, the fix needs physical firmware access — a site visit per affected device across 200 endpoints. | F14: Escalate — needs a physical firmware change. Flag early: every affected machine is a site visit.
A15: “I can't save to my USB stick” | B15: Baseline - Device Control | C15: Expected | D15: HIGH | E15: Writing to USB storage is denied — blocks 'copy the drawing set to a stick for site or the client'. DMA blocking can affect Thunderbolt docks and eGPU enclosures used on CAD workstations. | F15: Point the user to the agreed alternative (OneDrive/SharePoint). Do not disable per-device.
... A33: “I can't open an InPrivate window / cast to the meeting room screen” | B33: Edge minor UX set: InPrivate off · Google Cast off · background apps off · profile creation off | C33: Expected | D33: LOW | E33: No InPrivate windows (devs use these to test as an anonymous user), no Google Cast to meeting-room screens, no second browser profile for a personal or client-tenant login. | F33: Expected. Escalate only if meeting rooms depend on Cast.

Sheet Policy Mapping
A1: Policy file | B1: Category | C1: Name in Intune | D1: Graph object shape | E1: WB row | F1: Workbook policy name | G1: Platform | H1: CIS level | I1: Source | J1: Control domain | K1: NIST SP 800-53 Rev 5 | L1: ISO/IEC 27001:2022 | M1: Auditor rationale | N1: Mapping status | O1: Match method | P1: Match note
A2: ASR - BLOCK - Block Office applications from creating executable content | B2: 01_Defender_for_Endpoint (Windows + Linux) | C2: ASR - BLOCK - Block Office applications from creating executable content | D2: settings_catalog_policy | E2: 65 | F2: ASR - BLOCK - Block Office applications from creating executable content | G2: Windows 11 | H2: L1 | I2: Endpoint Security | J2: Attack Surface Reduction (ASR) | K2: SI-3 | L2: 8.7 | M2: Prevents Office from dropping executables to disk — closes macro dropper attack path | N2: mapped | O2: exact
A3: ASR - BLOCK - Block abuse of exploited vulnerable signed drivers (Device) | B3: 01_Defender_for_Endpoint (Windows + Linux) | C3: ASR - BLOCK - Block abuse of exploited vulnerable signed drivers (Device) | D3: settings_catalog_policy | E3: 68 | F3: ASR - BLOCK - Block abuse of exploited vulnerable signed drivers (Device) | G3: Windows 11 | H3: L1 | I3: Endpoint Security | J3: Attack Surface Reduction (ASR) | K3: SI-3 | L3: 8.7 | M3: Blocks BYOVD attacks — prevents exploitation of legitimately signed but vulnerable drivers | N3: mapped | O3: exact
A4: ASR - BLOCK - Block rebooting machine in Safe Mode | B4: 01_Defender_for_Endpoint (Windows + Linux) | C4: ASR - BLOCK - Block rebooting machine in Safe Mode | D4: settings_catalog_policy | E4: 70 | F4: ASR - BLOCK - Block rebooting machine in Safe Mode | G4: Windows 11 | H4: L2 | I4: Endpoint Security | J4: Attack Surface Reduction (ASR) | K4: SI-3 | L4: 8.7 | M4: Prevents malware from rebooting into Safe Mode to evade Defender — closes a common AV bypass technique | N4: mapped | O4: exact
A5: ASR - BLOCK - Enable Controlled Folder Access | B5: 01_Defender_for_Endpoint (Windows + Linux) | C5: ASR - BLOCK - Enable Controlled Folder Access | D5: settings_catalog_policy | E5: 71 | F5: ASR - BLOCK - Enable Controlled Folder Access | G5: Windows 11 | H5: L2 | I5: Endpoint Security | J5: Attack Surface Reduction (ASR) | K5: SI-3 | L5: 8.7 | M5: Set to Audit mode — monitors ransomware-style folder access without blocking. Provides detection evidence for SI-3 without risking false-positive blocks on legitimate apps | N5: mapped | O5: exact
A6: ASR - BLOCK - Use advanced protection against ransomware | B6: 01_Defender_for_Endpoint (Windows + Linux) | C6: ASR - BLOCK - Use advanced protection against ransomware | D6: settings_catalog_policy | E6: 59 | F6: ASR - BLOCK - Use advanced protection against ransomware | G6: Windows 11 | H6: L1 | I6: Endpoint Security | J6: Attack Surface Reduction (ASR) | K6: SI-3 | L6: 8.7 | M6: Ransomware protection specifically called out in ISO 8.7 and SI-3 guidance | N6: mapped | O6: exact
A7: Baseline - App and Browser Isolation | B7: 01_Defender_for_Endpoint (Windows + Linux) | C7: Baseline - App and Browser Isolation | D7: settings_catalog_policy | E7: 96 | F7: Baseline - App and Browser Isolation | G7: Windows 11 | H7: L1 | I7: Endpoint Security | J7: Malware Protection | K7: SI-7, SC-3 | L7: 8.7 | M7: Windows Defender Application Guard / exploit-protection settings - complements the existing ASR rule set. | N7: mapped | O7: exact
A8: Baseline - Chrome Microsoft Defender Browser Protection | B8: 01_Defender_for_Endpoint (Windows + Linux) | C8: Baseline - Chrome Microsoft Defender Browser Protection | D8: settings_catalog_policy | E8: 93 | F8: Baseline - Chrome Microsoft Defender Browser Protection | G8: Chrome | H8: L1 | I8: Endpoint Security | J8: Malware Protection | K8: SI-3, SC-8 | L8: 8.7 | M8: Extends Defender SmartScreen-equivalent protection into Chrome - closes the browser-protection gap on the non-Edge browser. | N8: mapped | O8: exact
A9: Baseline - Defender for Endpoint Linux | B9: 01_Defender_for_Endpoint (Windows + Linux) | C9: Baseline - Defender for Endpoint Linux | D9: settings_catalog_policy | E9: 88 | F9: Baseline - Defender for Endpoint Linux | G9: Linux | H9: L1 | I9: MDE | J9: Linux Endpoint Security | K9: SI-3, SI-2 | L9: 8.7, 8.8 | M9: The only enforceable Linux hardening lever native to Intune - configures AV/EDR behaviour on Linux endpoints via mdatp_managed.json. | N9: mapped | O9: whitespace
A10: Baseline - MDE Device Tag | B10: 01_Defender_for_Endpoint (Windows + Linux) | C10: Baseline - MDE Device Tag | D10: legacy_device_configuration | N10: UNMAPPED — no workbook row | O10: unmapped
A11: Baseline - Microsoft Defender Antivirus | B11: 01_Defender_for_Endpoint (Windows + Linux) | C11: Baseline - Microsoft Defender Antivirus | D11: settings_catalog_policy | E11: 18 | F11: Baseline - Microsoft Defender Antivirus | G11: Windows 11 | H11: L1 | I11: MDE | J11: Malware Protection | K11: SI-3, SI-2, SI-7 | L11: 8.7, 8.8 | M11: 33-setting comprehensive AV policy — covers realtime monitoring, behaviour monitoring, script scanning, network protection, PUA, cloud protection (MAPS), archive scanning, email scanning, scheduled scans, signature updates every 8h, CPU throttling, sample submission, local admin merge prevention. Replaces all individual CIS AV policies. Update channels (engine/platform/sig intelligence) set to Current — Defender always up to date. ⚠ Import via: Devices > Configuration (Settings Catalog) — MDE folder | N11: mapped | O11: exact
A12: Baseline - Microsoft Defender Update controls | B12: 01_Defender_for_Endpoint (Windows + Linux) | C12: Baseline - Defender Update controls | D12: settings_catalog_policy | E12: 90 | F12: Baseline - Microsoft Defender Update controls | G12: Windows 11 | H12: L1 | I12: MDE | J12: Patch Management | K12: SI-2, CM-6 | L12: 8.8 | M12: Governs signature/platform update cadence for Defender itself - closes a patch-management gap specific to the AV engine. | N12: mapped | O12: exact
A13: Baseline - Scareware Blocker in Microsoft Edge | B13: 01_Defender_for_Endpoint (Windows + Linux) | C13: Baseline - Scareware Blocker in Microsoft Edge | D13: settings_catalog_policy | E13: 94 | F13: Baseline - Scareware Blocker in Microsoft Edge | G13: Edge | H13: L1 | I13: Endpoint Security | J13: Malware Protection | K13: SI-3 | L13: 8.7 | M13: Blocks fake tech-support/scareware full-screen pages. Low functional impact, high auditor-visible value. | N13: mapped | O13: exact
A14: Baseline - Smartscreen Enhanced Phishing Protection Block Mode | B14: 01_Defender_for_Endpoint (Windows + Linux) | C14: Baseline - Smartscreen Enhanced Phishing Protection Block Mode | D14: settings_catalog_policy | N14: UNMAPPED — no workbook row | O14: unmapped
A15: Baseline - Windows Defender Security Experience | B15: 01_Defender_for_Endpoint (Windows + Linux) | C15: Baseline - Windows Security Experience | D15: settings_catalog_policy | E15: 19 | F15: Baseline - Windows Defender Security Experience | G15: Windows 11 | H15: L1 | I15: MDE | J15: Malware Protection | K15: SI-3, CM-7 | L15: 8.7, 8.9 | M15: Tamper Protection enabled — prevents users and malware from disabling Defender. Locks Security Center UI panels (family, health, network, notifications). Critical SI-3 control. ⚠ Import via: Devices > Configuration (Settings Catalog) — MDE folder | N15: mapped | O15: exact
A16: CISv3 - EDGE - L1 - Configure Microsoft Defender SmartScreen | B16: 01_Defender_for_Endpoint (Windows + Linux) | C16: CISv3 - EDGE - L1 - Configure Microsoft Defender SmartScreen | D16: settings_catalog_policy | E16: 74 | F16: CISv3 - EDGE - L1 - Configure Microsoft Defender SmartScreen | G16: Edge | H16: L1 | I16: CIS | J16: Edge Browser Security | K16: SI-3 | L16: 8.7, 8.23 | M16: Browser-level SmartScreen is the primary web filtering control — ISO 8.23 evidence | N16: mapped | O16: exact
A17: CISv3 - EDGE - L1 - Prevent bypassing Microsoft Defender SmartScreen prompts for sites | B17: 01_Defender_for_Endpoint (Windows + Linux) | C17: CISv3 - EDGE - L1 - Prevent bypassing Microsoft Defender SmartScreen prompts for sites | D17: settings_catalog_policy | E17: 111 | F17: CISv3 - EDGE - L1 - Prevent bypassing Microsoft Defender SmartScreen prompts for sites | G17: Edge | H17: L1 | I17: CIS | J17: Edge Browser Security | K17: SI-3 | L17: 8.7 | M17: Closes the 'click through the warning' bypass gap on the SmartScreen policy already deployed - pairs directly with an existing control. | N17: mapped | O17: exact
A18: CISv4 - WIN - L1 - ASR Block Adobe Reader from creating child processes | B18: 01_Defender_for_Endpoint (Windows + Linux) | C18: CISv4 - WIN - L1 - ASR: Block Adobe Reader from creating child processes | D18: settings_catalog_policy | E18: 63 | F18: ASR - BLOCK - Block Adobe Reader from creating child processes | G18: Windows 11 | H18: L1 | I18: Endpoint Security | J18: Attack Surface Reduction (ASR) | K18: SI-3 | L18: 8.7 | M18: Prevents PDF-based exploitation — closes a common document-based attack path | N18: mapped | O18: prefix
A19: CISv4 - WIN - L1 - ASR Block JavaScript or VBScript from launching downloaded executable content | B19: 01_Defender_for_Endpoint (Windows + Linux) | C19: CISv4 - WIN - L1 - ASR: Block JavaScript or VBScript from launching downloaded executable content | D19: settings_catalog_policy | E19: 64 | F19: ASR - BLOCK - Block JavaScript or VBScript from launching downloaded executable content | G19: Windows 11 | H19: L1 | I19: Endpoint Security | J19: Attack Surface Reduction (ASR) | K19: SI-3 | L19: 8.7 | M19: Blocks script-based malware delivery — covers a primary web-based attack vector | N19: mapped | O19: prefix
A20: CISv4 - WIN - L1 - ASR Block Office communication application from creating child processes | B20: 01_Defender_for_Endpoint (Windows + Linux) | C20: CISv4 - WIN - L1 - ASR: Block Office communication application from creating child processes | D20: settings_catalog_policy | E20: 66 | F20: ASR - BLOCK - Block Office communication application from creating child processes | G20: Windows 11 | H20: L1 | I20: Endpoint Security | J20: Attack Surface Reduction (ASR) | K20: SI-3 | L20: 8.7 | M20: Blocks Outlook/Teams from spawning child processes — prevents email client exploitation | N20: mapped | O20: prefix
A21: CISv4 - WIN - L1 - ASR Block Win32 API calls from Office macros | B21: 01_Defender_for_Endpoint (Windows + Linux) | C21: CISv4 - WIN - L1 - ASR: Block Win32 API calls from Office macros | D21: settings_catalog_policy | E21: 58 | F21: ASR - BLOCK - Block Win32 API calls from Office macros | G21: Windows 11 | H21: L1 | I21: Endpoint Security | J21: Attack Surface Reduction (ASR) | K21: SI-3 | L21: 8.7 | M21: Macro-based attacks are a top threat vector — directly evidences ISO 8.7 macro controls | N21: mapped | O21: prefix
A22: CISv4 - WIN - L1 - ASR Block all Office applications from creating child processes | B22: 01_Defender_for_Endpoint (Windows + Linux) | C22: CISv4 - WIN - L1 - ASR: Block all Office applications from creating child processes | D22: settings_catalog_policy | E22: 67 | F22: ASR - BLOCK - Block all Office applications from creating child processes | G22: Windows 11 | H22: L1 | I22: Endpoint Security | J22: Attack Surface Reduction (ASR) | K22: SI-3 | L22: 8.7 | M22: Blanket block on Office spawning any child process — strongest Office attack surface control | N22: mapped | O22: prefix
A23: CISv4 - WIN - L1 - ASR Block credential stealing from the Windows local security authority subsystem | B23: 01_Defender_for_Endpoint (Windows + Linux) | C23: CISv4 - WIN - L1 - ASR: Block credential stealing from the Windows local security authority subsystem | D23: settings_catalog_policy | E23: 56 | F23: ASR - BLOCK - Block credential stealing from the Windows local security authority subsystem | G23: Windows 11 | H23: L1 | I23: Endpoint Security | J23: Attack Surface Reduction (ASR) | K23: SI-3, SI-16 | L23: 8.7 | M23: Blocks LSASS dumping — highest-value ASR rule. ES BLOCK policy used: proper template reference, enforced block mode | N23: mapped | O23: prefix
A24: CISv4 - WIN - L1 - ASR Block executable content from email client and webmail | B24: 01_Defender_for_Endpoint (Windows + Linux) | C24: CISv4 - WIN - L1 - ASR: Block executable content from email client and webmail | D24: settings_catalog_policy | E24: 57 | F24: ASR - BLOCK - Block executable content from email client and webmail | G24: Windows 11 | H24: L1 | I24: Endpoint Security | J24: Attack Surface Reduction (ASR) | K24: SI-3 | L24: 8.7 | M24: Email is the primary malware delivery vector — enforced block mode with template reference | N24: mapped | O24: prefix
A25: CISv4 - WIN - L1 - ASR Block executable files from running unless they meet a prevalence, age, or trusted list criterion' | B25: 01_Defender_for_Endpoint (Windows + Linux) | C25: CISv4 - WIN - L1 - ASR: Block executable files from running unless they meet a prevalence, age, or trusted list criterion' | D25: settings_catalog_policy | N25: UNMAPPED — no workbook row | O25: unmapped
A26: CISv4 - WIN - L1 - ASR Block execution of potentially obfuscated scripts | B26: 01_Defender_for_Endpoint (Windows + Linux) | C26: CISv4 - WIN - L1 - ASR: Block execution of potentially obfuscated scripts | D26: settings_catalog_policy | N26: UNMAPPED — no workbook row | O26: unmapped
A27: CISv4 - WIN - L1 - ASR Block persistence through WMI event subscription | B27: 01_Defender_for_Endpoint (Windows + Linux) | C27: CISv4 - WIN - L1 - ASR: Block persistence through WMI event subscription | D27: settings_catalog_policy | E27: 69 | F27: ASR - BLOCK - Block persistence through WMI event subscription | G27: Windows 11 | H27: L1 | I27: Endpoint Security | J27: Attack Surface Reduction (ASR) | K27: SI-3 | L27: 8.7 | M27: Blocks WMI-based persistence — a favourite technique for fileless malware and APT actors | N27: mapped | O27: prefix
A28: CISv4 - WIN - L1 - ASR Block process creations originating from PSExec and WMI commands | B28: 01_Defender_for_Endpoint (Windows + Linux) | C28: CISv4 - WIN - L1 - ASR: Block process creations originating from PSExec and WMI commands | D28: settings_catalog_policy | E28: 61 | F28: CISv4 - WIN - L1 - ASR Block process creations originating from PSExec and WMI commands | G28: Windows 11 | H28: L1 | I28: CIS | J28: Attack Surface Reduction (ASR) | K28: SI-3 | L28: 8.7 | M28: Blocks living-off-the-land lateral movement via PSExec and WMI — CIS L1 version used (no ES BLOCK equivalent exists for this specific rule) | N28: mapped | O28: exact
A29: CISv4 - WIN - L1 - ASR Block untrusted and unsigned processes that run from USB | B29: 01_Defender_for_Endpoint (Windows + Linux) | C29: CISv4 - WIN - L1 - ASR: Block untrusted and unsigned processes that run from USB | D29: settings_catalog_policy | E29: 62 | F29: ASR - BLOCK - Block untrusted and unsigned processes that run from USB | G29: Windows 11 | H29: L1 | I29: Endpoint Security | J29: Attack Surface Reduction (ASR) | K29: SI-3, MP-7 | L29: 8.7 | M29: Blocks malware execution from USB drives — ES BLOCK version with template reference | N29: mapped | O29: prefix
A30: CISv4 - WIN - L2 - Enable File Hash Computation | B30: 01_Defender_for_Endpoint (Windows + Linux) | C30: CISv4 - WIN - L2 - Enable File Hash Computation | D30: settings_catalog_policy | E30: 20 | F30: CISv4 - WIN - L2 - Enable File Hash Computation | G30: Windows 11 | H30: L2 | I30: CIS | J30: Malware Protection | K30: SI-3, SI-7 | L30: 8.7 | M30: Defender computes file hashes for threat intelligence — invisible to users, strengthens SI-3 and SI-7 evidence | N30: mapped | O30: exact
A31: Baseline - Device Password Policy (Consolidated) | B31: 02_Windows_CIS_Benchmark_Hardening | C31: Baseline - Device Password Policy (Consolidated) | D31: settings_catalog_policy | E31: 1 | F31: Baseline - Device Password Policy (Consolidated) | G31: Windows 11 | H31: L1 | I31: CIS | J31: Authentication & Account Security | K31: IA-5, AC-11, AC-7 | L31: 8.5, 8.1, 5.17 | M31: Consolidates the 6 separate 'Device Password Enabled...' policies from the original baseline into one. The DeviceLock CSP requires all child settings (min length, complexity, lockout, inactivity, history) to travel together under one parent setting — deploying the original 6 as separate policies to the same device causes a genuine Intune Settings Catalog conflict, since each file reset the others' settings back to schema defaults. Fixed 2026-09: min length 14, alphanumeric required, 5 failed attempts, 15 min inactivity, 24-password history, enabled. | N31: mapped | O31: exact
A32: CISv4 - WIN - L1 - 'User Account Control Behavior of the elevation prompt for standard users | B32: 02_Windows_CIS_Benchmark_Hardening | C32: CISv4 - WIN - L1 - 'User Account Control: Behavior of the elevation prompt for standard users | D32: settings_catalog_policy | E32: 31 | F32: CISv4 - WIN - L1 - 'User Account Control Behavior of the elevation prompt for standard users | G32: Windows 11 | H32: L1 | I32: CIS | J32: UAC & Privileged Access | K32: AC-6 | L32: 8.2 | M32: Ensures standard users cannot self-elevate — AC-6 least privilege enforcement | N32: mapped | O32: exact
A33: CISv4 - WIN - L1 - Accounts Enable Guest account status | B33: 02_Windows_CIS_Benchmark_Hardening | C33: CISv4 - WIN - L1 - Accounts: Enable Guest account status | D33: settings_catalog_policy | E33: 2 | F33: CISv4 - WIN - L1 - Accounts Enable Guest account status | G33: Windows 11 | H33: L1 | I33: CIS | J33: Authentication & Account Security | K33: AC-2 | L33: 5.16, 8.2 | M33: Disabling guest access is a mandatory AC-2 control — auditors always check this | N33: mapped | O33: exact
A34: CISv4 - WIN - L1 - Accounts Limit local account use of blank passwords to console logon only' | B34: 02_Windows_CIS_Benchmark_Hardening | C34: CISv4 - WIN - L1 - Accounts: Limit local account use of blank passwords to console logon only' | D34: settings_catalog_policy | E34: 3 | F34: CISv4 - WIN - L1 - Accounts Limit local account use of blank passwords to console logon only' | G34: Windows 11 | H34: L1 | I34: CIS | J34: Authentication & Account Security | K34: IA-5 | L34: 8.5, 5.17 | M34: Blocks remote access with blank passwords — critical IA-5 evidence | N34: mapped | O34: exact
A35: CISv4 - WIN - L1 - Accounts Rename administrator account | B35: 02_Windows_CIS_Benchmark_Hardening | C35: CISv4 - WIN - L1 - Accounts: Rename administrator account | D35: settings_catalog_policy | E35: 4 | F35: CISv4 - WIN - L1 - Accounts Rename administrator account | G35: Windows 11 | H35: L1 | I35: CIS | J35: Authentication & Account Security | K35: AC-2, AC-6 | L35: 5.16, 8.2 | M35: Removes predictable attack target — standard auditor check for AC-2/AC-6 | N35: mapped | O35: exact
A36: CISv4 - WIN - L1 - Allow Basic authentication WinRM Client | B36: 02_Windows_CIS_Benchmark_Hardening | C36: CISv4 - WIN - L1 - Allow Basic authentication WinRM Client | D36: settings_catalog_policy | N36: UNMAPPED — no workbook row | O36: unmapped
A37: CISv4 - WIN - L1 - Allow Indexing Encrypted Stores Or Items | B37: 02_Windows_CIS_Benchmark_Hardening | C37: CISv4 - WIN - L1 - Allow Indexing Encrypted Stores Or Items | D37: settings_catalog_policy | N37: UNMAPPED — no workbook row | O37: unmapped
A38: CISv4 - WIN - L1 - Always prompt for password upon connection | B38: 02_Windows_CIS_Benchmark_Hardening | C38: CISv4 - WIN - L1 - Always prompt for password upon connection | D38: settings_catalog_policy | E38: 41 | F38: CISv4 - WIN - L1 - Always prompt for password upon connection | G38: Windows 11 | H38: L1 | I38: CIS | J38: Remote Access | K38: AC-17, IA-2 | L38: 8.5 | M38: Prevents credential caching on RDP reconnect — AC-17 and ISO 8.5 evidence | N38: mapped | O38: exact
A39: CISv4 - WIN - L1 - Apply UAC restrictions to local accounts on network logons | B39: 02_Windows_CIS_Benchmark_Hardening | C39: CISv4 - WIN - L1 - Apply UAC restrictions to local accounts on network logons | D39: settings_catalog_policy | E39: 32 | F39: CISv4 - WIN - L1 - Apply UAC restrictions to local accounts on network logons | G39: Windows 11 | H39: L1 | I39: CIS | J39: UAC & Privileged Access | K39: AC-6, AC-3 | L39: 8.2 | M39: Prevents pass-the-hash lateral movement via local admin — critical AC-6 network control | N39: mapped | O39: exact
A40: CISv4 - WIN - L1 - Configure Lsa Protected Process is set to 'Enabled with UEFI Lock | B40: 02_Windows_CIS_Benchmark_Hardening | C40: CISv4 - WIN - L1 - Configure Lsa Protected Process is set to 'Enabled with UEFI Lock... | D40: settings_catalog_policy | E40: 27 | F40: CISv4 - WIN - L1 - Configure Lsa Protected Process is set to 'Enabled with UEFI Lock | G40: Windows 11 | H40: L1 | I40: CIS | J40: Credential Protection | K40: SC-3, SI-16 | L40: 8.1 | M40: LSA protection prevents credential dumping — key evidence for SI-16 and ISO 8.1 | N40: mapped | O40: exact
A41: CISv4 - WIN - L1 - Configure SMB v1 client driver | B41: 02_Windows_CIS_Benchmark_Hardening | C41: CISv4 - WIN - L1 - Configure SMB v1 client driver | D41: settings_catalog_policy | E41: 35 | F41: CISv4 - WIN - L1 - Configure SMB v1 client driver | G41: Windows 11 | H41: L1 | I41: CIS | J41: Network Security | K41: CM-7, SC-8 | L41: 8.9, 8.20 | M41: Disabling SMBv1 closes the EternalBlue attack surface — standard audit expectation | N41: mapped | O41: exact
A42: CISv4 - WIN - L1 - Configure SMB v1 server | B42: 02_Windows_CIS_Benchmark_Hardening | C42: CISv4 - WIN - L1 - Configure SMB v1 server | D42: settings_catalog_policy | E42: 36 | F42: CISv4 - WIN - L1 - Configure SMB v1 server | G42: Windows 11 | H42: L1 | I42: CIS | J42: Network Security | K42: CM-7, SC-8 | L42: 8.9, 8.20 | M42: Server-side SMBv1 disable — auditors check both client and server settings | N42: mapped | O42: exact
A43: CISv4 - WIN - L1 - Credential Guard | B43: 02_Windows_CIS_Benchmark_Hardening | C43: CISv4 - WIN - L1 - Credential Guard | D43: settings_catalog_policy | N43: UNMAPPED — no workbook row | O43: unmapped
A44: CISv4 - WIN - L1 - Interactive logon Machine inactivity limit | B44: 02_Windows_CIS_Benchmark_Hardening | C44: CISv4 - WIN - L1 - Interactive logon: Machine inactivity limit | D44: settings_catalog_policy | E44: 46 | F44: CISv4 - WIN - L1 - Interactive logon Machine inactivity limit | G44: Windows 11 | H44: L1 | I44: CIS | J44: Screen Lock & Session | K44: AC-11 | L44: 8.1 | M44: Idle timeout lockout — one of the most commonly tested physical security controls | N44: mapped | O44: exact
A45: CISv4 - WIN - L1 - Interactive logon Smart card removal behavior | B45: 02_Windows_CIS_Benchmark_Hardening | C45: CISv4 - WIN - L1 - Interactive logon: Smart card removal behavior | D45: settings_catalog_policy | E45: 47 | F45: CISv4 - WIN - L1 - Interactive logon Smart card removal behavior | G45: Windows 11 | H45: L1 | I45: CIS | J45: Screen Lock & Session | K45: AC-11 | L45: 8.1 | M45: Locks workstation on smart card removal — supports AC-11 session termination | N45: mapped | O45: exact
A46: CISv4 - WIN - L1 - MSS (AutoAdminLogon) Enable Automatic Logon (not recommended) | B46: 02_Windows_CIS_Benchmark_Hardening | C46: CISv4 - WIN - L1 - MSS: (AutoAdminLogon) Enable Automatic Logon (not recommended) | D46: settings_catalog_policy | N46: UNMAPPED — no workbook row | O46: unmapped
A47: CISv4 - WIN - L1 - Microsoft network client Digitally sign communications (always) | B47: 02_Windows_CIS_Benchmark_Hardening | C47: CISv4 - WIN - L1 - Microsoft network client: Digitally sign communications (always) | D47: settings_catalog_policy | E47: 37 | F47: CISv4 - WIN - L1 - Microsoft network client Digitally sign communications (always) | G47: Windows 11 | H47: L1 | I47: CIS | J47: Network Security | K47: SC-8 | L47: 8.20 | M47: Mandates SMB signing — prevents relay attacks, directly evidences SC-8 | N47: mapped | O47: exact
A48: CISv4 - WIN - L1 - Microsoft network server Digitally sign communications (always) | B48: 02_Windows_CIS_Benchmark_Hardening | C48: CISv4 - WIN - L1 - Microsoft network server: Digitally sign communications (always) | D48: settings_catalog_policy | N48: UNMAPPED — no workbook row | O48: unmapped
A49: CISv4 - WIN - L1 - Network security Do not store LAN Manager hash value on next password change | B49: 02_Windows_CIS_Benchmark_Hardening | C49: CISv4 - WIN - L1 - Network security: Do not store LAN Manager hash value on next password change | D49: settings_catalog_policy | E49: 28 | F49: CISv4 - WIN - L1 - Network security Do not store LAN Manager hash value on next password change | G49: Windows 11 | H49: L1 | I49: CIS | J49: Credential Protection | K49: IA-5 | L49: 8.5, 5.17 | M49: Eliminates weak LM hash storage — directly satisfies IA-5 and ISO 5.17 | N49: mapped | O49: exact
A50: CISv4 - WIN - L1 - Network security LAN Manager authentication level | B50: 02_Windows_CIS_Benchmark_Hardening | C50: CISv4 - WIN - L1 - Network security: LAN Manager authentication level | D50: settings_catalog_policy | E50: 34 | F50: CISv4 - WIN - L1 - Network security LAN Manager authentication level | G50: Windows 11 | H50: L1 | I50: CIS | J50: Network Security | K50: IA-3, SC-8 | L50: 8.5, 8.20 | M50: Sets NTLMv2-only — eliminates weak auth protocols, satisfies SC-8 and ISO 8.5 | N50: mapped | O50: exact
A51: CISv4 - WIN - L1 - Prevent the use of security questions for local accounts | B51: 02_Windows_CIS_Benchmark_Hardening | C51: CISv4 - WIN - L1 - Prevent the use of security questions for local accounts | D51: settings_catalog_policy | E51: 5 | F51: CISv4 - WIN - L1 - Prevent the use of security questions for local accounts | G51: Windows 11 | H51: L1 | I51: CIS | J51: Authentication & Account Security | K51: IA-5 | L51: 8.5, 5.17 | M51: Eliminates weak authenticator fallback — directly addresses IA-5 and ISO 5.17 | N51: mapped | O51: exact
A52: CISv4 - WIN - L1 - Require a password when a computer wakes (plugged in) | B52: 02_Windows_CIS_Benchmark_Hardening | C52: CISv4 - WIN - L1 - Require a password when a computer wakes (plugged in) | D52: settings_catalog_policy | E52: 48 | F52: CISv4 - WIN - L1 - Require a password when a computer wakes (plugged in) | G52: Windows 11 | H52: L1 | I52: CIS | J52: Screen Lock & Session | K52: AC-11 | L52: 8.1 | M52: Ensures wake-from-sleep requires re-authentication — AC-11 evidence for auditors | N52: mapped | O52: exact
A53: CISv4 - WIN - L1 - Require secure RPC communication | B53: 02_Windows_CIS_Benchmark_Hardening | C53: CISv4 - WIN - L1 - Require secure RPC communication | D53: settings_catalog_policy | E53: 42 | F53: CISv4 - WIN - L1 - Require secure RPC communication | G53: Windows 11 | H53: L1 | I53: CIS | J53: Remote Access | K53: SC-8 | L53: 8.20 | M53: Authenticated and encrypted RPC — closes unauthenticated RPC exploitation path | N53: mapped | O53: exact
A54: CISv4 - WIN - L1 - Require user authentication for remote connections by using Network Level Authentication | B54: 02_Windows_CIS_Benchmark_Hardening | C54: CISv4 - WIN - L1 - Require user authentication for remote connections by using Network Level Authentication | D54: settings_catalog_policy | E54: 39 | F54: CISv4 - WIN - L1 - Require user authentication for remote connections by using Network Level Authentication | G54: Windows 11 | H54: L1 | I54: CIS | J54: Remote Access | K54: AC-17, IA-2 | L54: 8.5, 8.20 | M54: NLA for RDP is one of the first remote access controls auditors test | N54: mapped | O54: exact
A55: CISv4 - WIN - L1 - Set client connection encryption level | B55: 02_Windows_CIS_Benchmark_Hardening | C55: CISv4 - WIN - L1 - Set client connection encryption level | D55: settings_catalog_policy | E55: 40 | F55: CISv4 - WIN - L1 - Set client connection encryption level | G55: Windows 11 | H55: L1 | I55: CIS | J55: Remote Access | K55: AC-17, SC-8 | L55: 8.20 | M55: Forces high encryption on RDP sessions — directly evidences SC-8 for remote access | N55: mapped | O55: exact
A56: CISv4 - WIN - L1 - User Account Control Behavior of the elevation prompt for administrators | B56: 02_Windows_CIS_Benchmark_Hardening | C56: CISv4 - WIN - L1 - User Account Control: Behavior of the elevation prompt for administrators | D56: settings_catalog_policy | E56: 30 | F56: CISv4 - WIN - L1 - User Account Control Behavior of the elevation prompt for administrators | G56: Windows 11 | H56: L1 | I56: CIS | J56: UAC & Privileged Access | K56: AC-6 | L56: 8.2 | M56: Controls how admin elevation is triggered — auditors verify prompt is not bypassed | N56: mapped | O56: exact
A57: CISv4 - WIN - L1 - User Account Control Run all administrators in Admin Approval Mode | B57: 02_Windows_CIS_Benchmark_Hardening | C57: CISv4 - WIN - L1 - User Account Control: Run all administrators in Admin Approval Mode | D57: settings_catalog_policy | E57: 29 | F57: CISv4 - WIN - L1 - User Account Control Run all administrators in Admin Approval Mode | G57: Windows 11 | H57: L1 | I57: CIS | J57: UAC & Privileged Access | K57: AC-6 | L57: 8.2 | M57: Admin Approval Mode is the cornerstone of least-privilege enforcement on Windows | N57: mapped | O57: exact
A58: CISv4 - WIN - L1 - WDigest Authentication | B58: 02_Windows_CIS_Benchmark_Hardening | C58: CISv4 - WIN - L1 - WDigest Authentication | D58: settings_catalog_policy | E58: 26 | F58: CISv4 - WIN - L1 - WDigest Authentication | G58: Windows 11 | H58: L1 | I58: CIS | J58: Credential Protection | K58: IA-5, SC-28 | L58: 8.5 | M58: Disabling WDigest prevents cleartext credential caching — critical IA-5 and ISO 8.5 control | N58: mapped | O58: exact
A59: CISv4 - WIN - L2 - Set time limit for active but idle Remote Desktop Services sessions | B59: 02_Windows_CIS_Benchmark_Hardening | C59: CISv4 - WIN - L2 - Set time limit for active but idle Remote Desktop Services sessions | D59: settings_catalog_policy | E59: 44 | F59: CISv4 - WIN - L2 - Set time limit for active but idle Remote Desktop Services sessions | G59: Windows 11 | H59: L2 | I59: CIS | J59: Remote Access | K59: AC-11, AC-17 | L59: 8.1 | M59: Idle RDS session timeout — zero user impact, directly satisfies AC-11 and ISO 8.1 | N59: mapped | O59: exact
A60: CISv4 - WIN - L2 - Set time limit for disconnected sessions | B60: 02_Windows_CIS_Benchmark_Hardening | C60: CISv4 - WIN - L2 - Set time limit for disconnected sessions | D60: settings_catalog_policy | E60: 45 | F60: CISv4 - WIN - L2 - Set time limit for disconnected sessions | G60: Windows 11 | H60: L2 | I60: CIS | J60: Remote Access | K60: AC-11, AC-17 | L60: 8.1 | M60: Cleans up disconnected sessions — prevents abandoned authenticated sessions, AC-11 evidence | N60: mapped | O60: exact
... A64: CISv4 - WIN - L1 - Audit Changes to Audit Policy | B64: 03_Audit_and_Logging | C64: CISv4 - WIN - L1 - Audit Changes to Audit Policy | D64: settings_catalog_policy | E64: 13 | F64: CISv4 - WIN - L1 - Audit Changes to Audit Policy | G64: Windows 11 | H64: L1 | I64: CIS | J64: Audit & Logging | K64: AU-2, AU-9 | L64: 8.15 | M64: Detects tampering with audit config — required for AU-9 protection of logs | N64: mapped | O64: exact
A65: CISv4 - WIN - L1 - Audit Special Logon | B65: 03_Audit_and_Logging | C65: CISv4 - WIN - L1 - Audit Special Logon | D65: settings_catalog_policy | N65: UNMAPPED — no workbook row | O65: unmapped
A66: CISv4 - WIN - L1 - Audit User Account Management | B66: 03_Audit_and_Logging | C66: CISv4 - WIN - L1 - Audit User Account Management | D66: settings_catalog_policy | E66: 10 | F66: CISv4 - WIN - L1 - Audit User Account Management | G66: Windows 11 | H66: L1 | I66: CIS | J66: Audit & Logging | K66: AU-2, AU-12 | L66: 8.15 | M66: Captures account creation/modification — required for AC-2 audit trail | N66: mapped | O66: exact
A67: CISv4 - WIN - L1 - Object Access Audit Removable Storage | B67: 03_Audit_and_Logging | C67: CISv4 - WIN - L1 - Object Access Audit Removable Storage | D67: settings_catalog_policy | E67: 15 | F67: CISv4 - WIN - L1 - Object Access Audit Removable Storage | G67: Windows 11 | H67: L1 | I67: CIS | J67: Audit & Logging | K67: AU-2, AU-12 | L67: 8.15 | M67: Audits all removable storage access events — ISO 8.15 evidence and forensic trail for USB activity | N67: mapped | O67: exact
A68: CISv4 - WIN - L1 - Privilege Use Audit Sensitive Privilege Use | B68: 03_Audit_and_Logging | C68: CISv4 - WIN - L1 - Privilege Use Audit Sensitive Privilege Use | D68: settings_catalog_policy | E68: 12 | F68: CISv4 - WIN - L1 - Privilege Use Audit Sensitive Privilege Use | G68: Windows 11 | H68: L1 | I68: CIS | J68: Audit & Logging | K68: AU-2, AU-12 | L68: 8.15 | M68: Logs use of sensitive privileges — directly satisfies AU-2 and ISO 8.16 | N68: mapped | O68: exact
A69: CISv4 - WIN - L1 - Specify the maximum log file size (KB) Security | B69: 03_Audit_and_Logging | C69: CISv4 - WIN - L1 - Specify the maximum log file size (KB) Security | D69: settings_catalog_policy | E69: 14 | F69: CISv4 - WIN - L1 - Specify the maximum log file size (KB) Security | G69: Windows 11 | H69: L1 | I69: CIS | J69: Audit & Logging | K69: AU-11 | L69: 8.15 | M69: Ensures logs are retained and not overwritten — AU-11 retention evidence | N69: mapped | O69: exact
A70: CISv4 - WIN - L2 - Turn on PowerShell Script Block Logging | B70: 03_Audit_and_Logging | C70: CISv4 - WIN - L2 - Turn on PowerShell Script Block Logging | D70: settings_catalog_policy | E70: 16 | F70: CISv4 - WIN - L2 - Turn on PowerShell Script Block Logging | G70: Windows 11 | H70: L2 | I70: CIS | J70: Audit & Logging | K70: AU-2, AU-12 | L70: 8.15 | M70: Logs every PowerShell command executed — zero user impact, critical for incident investigation and AU-2 evidence | N70: mapped | O70: exact
A71: CISv4 - WIN - L2 - Turn on PowerShell Transcription | B71: 03_Audit_and_Logging | C71: CISv4 - WIN - L2 - Turn on PowerShell Transcription | D71: settings_catalog_policy | E71: 17 | F71: CISv4 - WIN - L2 - Turn on PowerShell Transcription | G71: Windows 11 | H71: L2 | I71: CIS | J71: Audit & Logging | K71: AU-2, AU-12 | L71: 8.15 | M71: Full PowerShell session transcripts — invisible to users, strongest forensic audit trail available on Windows | N71: mapped | O71: exact
A72: Baseline - Account Protection | B72: 04_Identity_and_Authentication | C72: Baseline - Account Protection | D72: endpoint_security_intent | E72: 95 | F72: Baseline - Account Protection | G72: Windows 11 | H72: L1 | I72: Endpoint Security | J72: UAC & Privileged Access | K72: AC-6, IA-2 | L72: 8.2 | M72: Microsoft's bundled account-protection template (Windows Hello / credential-guard-adjacent controls). | N72: mapped | O72: exact
A73: CISv4 - WIN - L2 - Support device authentication using certificate | B73: 04_Identity_and_Authentication | C73: CISv4 - WIN - L2 - Support device authentication using certificate | D73: settings_catalog_policy | E73: 6 | F73: CISv4 - WIN - L2 - Support device authentication using certificate | G73: Windows 11 | H73: L2 | I73: CIS | J73: Authentication & Account Security | K73: IA-3 | L73: 8.5 | M73: Certificate-based device authentication strengthens IA-3 — no user-facing impact | N73: mapped | O73: exact
A74: Baseline - Block add MSA accounts and non-MSA accounts | B74: 05_Tenant_and_Account_Access_Control | C74: Baseline - Block add MSA accounts and non-MSA accounts | D74: settings_catalog_policy | E74: 86 | F74: Baseline - Block add MSA accounts and non-MSA accounts | G74: Windows 11 | H74: L1 | I74: Modern Workplace | J74: Identity & Account Control | K74: AC-2, IA-8 | L74: 5.16, 8.5 | M74: Blocks personal Microsoft accounts and non-Microsoft accounts at OS level — prevents users signing into Edge or apps with personal credentials. Deploy as-is. ⚠ Import via: Devices > Configuration (Settings Catalog) | N74: mapped | O74: exact
A75: Baseline - One Drive management settings | B75: 05_Tenant_and_Account_Access_Control | C75: Baseline - One Drive management settings | D75: settings_catalog_policy | E75: 87 | F75: Baseline - One Drive management settings | G75: Windows 11 | H75: L2 | I75: Modern Workplace | J75: Identity & Account Control | K75: AC-2, AC-3 | L75: 5.15, 8.3 | M75: Restricts OneDrive to org tenant only via allowtenantlist — prevents personal OneDrive sign-in. Also includes mass delete protection and auto-mount of Teams sites. ⚠ REQUIRES CUSTOMISATION: Add customer Entra Tenant ID to allowtenantlist before deploying. ⚠ Import via: Devices > Configuration (Settings Catalog) | N75: mapped | O75: exact
A76: Baseline - Teams - Restrict sign in to Teams to accounts in specific tenants | B76: 05_Tenant_and_Account_Access_Control | C76: Baseline - Teams - Restrict sign in to Teams to accounts in specific tenants | D76: settings_catalog_policy | N76: UNMAPPED — no workbook row | O76: unmapped
A77: Baseline - Bitlocker Policy | B77: 06_Data_Encryption | C77: Baseline - Bitlocker Policy | D77: endpoint_security_intent | E77: 22 | F77: Baseline - Bitlocker Policy | G77: Windows 11 | H77: L1 | I77: Endpoint Security | J77: Encryption at Rest | K77: SC-28, MP-5 | L77: 8.24 | M77: ENFORCES BitLocker on OS drive (XTS-AES 256), fixed drives, and requires BitLocker To Go on USB drives before write access is granted. Recovery keys escrowed to Entra ID. Silent deployment — no user prompt. ⚠ Import via: Endpoint Security > Disk Encryption (not Settings Catalog) | N77: mapped | O77: exact
A78: Baseline - Linux - Device Encryption | B78: 06_Data_Encryption | C78: Baseline - Linux - Device Encryption | D78: compliance_policy | N78: UNMAPPED — no workbook row | O78: unmapped
A79: Baseline - Personal Data Encryption | B79: 06_Data_Encryption | C79: Baseline - Personal Data Encryption | D79: settings_catalog_policy | E79: 98 | F79: Baseline - Personal Data Encryption | G79: Windows 11 | H79: L2 | I79: Endpoint Security | J79: Encryption at Rest | K79: SC-28, MP-5 | L79: 8.24 | M79: File-level encryption tied to Windows Hello sign-in - complements rather than conflicts with BitLocker. Roll out alongside WHFB. | N79: mapped | O79: exact
A80: CISv4 - Choose how BitLocker-protected operating system drives can be recovered Require 48-digit recovery password | B80: 06_Data_Encryption | C80: CISv4 - Choose how BitLocker-protected operating system drives can be recovered Require 48-digit recovery password | D80: settings_catalog_policy | E80: 23 | F80: CISv4 - Choose how BitLocker-protected operating system drives can be recovered Require 48-digit recovery password | G80: Windows 11 | H80: L1 | I80: CIS | J80: Encryption at Rest | K80: SC-28 | L80: 8.24 | M80: Configures 48-digit recovery password requirement — complements the BitLocker enforcement policy above | N80: mapped | O80: exact
A81: Baseline - SSL Cipher Suite Order | B81: 07_Firewall_and_Network_Security | C81: Baseline - SSL Cipher Suite Order | D81: settings_catalog_policy | E81: 184 | F81: Baseline - SSL Cipher Suite Order | G81: Windows 11 | H81: L1 | I81: Modern Workplace | J81: Network Security | K81: SC-8, SC-13 | L81: 8.24 | M81: Straightforward network-hardening win. | N81: mapped | O81: exact
A82: Baseline - Windows - Firewall | B82: 07_Firewall_and_Network_Security | C82: Baseline - Windows - Firewall | D82: settings_catalog_policy | N82: UNMAPPED — no workbook row | O82: unmapped
A83: Baseline - Device Control | B83: 08_Removable_Media_and_Device_Control | C83: Baseline - Device Control | D83: settings_catalog_policy | N83: UNMAPPED — no workbook row | O83: unmapped
A84: CISv4 - WIN - L1 - Disallow Autoplay for non-volume devices | B84: 08_Removable_Media_and_Device_Control | C84: CISv4 - WIN - L1 - Disallow Autoplay for non-volume devices | D84: settings_catalog_policy | E84: 50 | F84: CISv4 - WIN - L1 - Disallow Autoplay for non-volume devices | G84: Windows 11 | H84: L1 | I84: CIS | J84: Removable Media & USB | K84: MP-7, CM-7 | L84: 8.9 | M84: Extends autoplay block to non-volume devices like phones — closes MP-7 gap | N84: mapped | O84: exact
A85: CISv4 - WIN - L1 - Turn off Autoplay | B85: 08_Removable_Media_and_Device_Control | C85: CISv4 - WIN - L1 - Turn off Autoplay | D85: settings_catalog_policy | N85: UNMAPPED — no workbook row | O85: unmapped
A86: CISv4 - WIN - L1 - Allow Auto Update | B86: 09_Patch_Management | C86: CISv4 - WIN - L1 - Allow Auto Update | D86: settings_catalog_policy | E86: 51 | F86: CISv4 - WIN - L1 - Allow Auto Update | G86: Windows 11 | H86: L1 | I86: CIS | J86: Patch Management | K86: SI-2 | L86: 8.8 | M86: Automatic updates is the primary SI-2 flaw remediation evidence on endpoints | N86: mapped | O86: exact
A87: CISv4 - WIN - L1 - Defer Feature Updates Period in Days | B87: 09_Patch_Management | C87: CISv4 - WIN - L1 - Defer Feature Updates Period in Days | D87: settings_catalog_policy | E87: 54 | F87: CISv4 - WIN - L1 - Defer Feature Updates Period in Days | G87: Windows 11 | H87: L1 | I87: CIS | J87: Patch Management | K87: SI-2 | L87: 8.8 | M87: Controlled deferral of Feature Updates — complements Quality Updates deferral for a complete managed update posture | N87: mapped | O87: exact
A88: CISv4 - WIN - L1 - Manage preview builds | B88: 09_Patch_Management | C88: CISv4 - WIN - L1 - Manage preview builds | D88: settings_catalog_policy | N88: UNMAPPED — no workbook row | O88: unmapped
A89: CISv4 - WIN - L1 - Pause Updates | B89: 09_Patch_Management | C89: CISv4 - WIN - L1 - Pause Updates | D89: settings_catalog_policy | E89: 53 | F89: CISv4 - WIN - L1 - Pause Updates | G89: Windows 11 | H89: L1 | I89: CIS | J89: Patch Management | K89: SI-2 | L89: 8.8 | M89: Prevents users from pausing Windows Updates — without this users can bypass update compliance for up to 5 weeks | N89: mapped | O89: exact
A90: CISv4 - WIN - L1 - Scheduled Install Day | B90: 09_Patch_Management | C90: CISv4 - WIN - L1 - Scheduled Install Day | D90: settings_catalog_policy | N90: UNMAPPED — no workbook row | O90: unmapped
A91: Baseline - Disable Xbox services | B91: 10_Privacy_and_AI_Data_Governance | C91: Baseline - Disable Xbox services | D91: settings_catalog_policy | E91: 190 | F91: Baseline - Disable Xbox services | G91: Windows 11 | H91: L1 | I91: Modern Workplace | J91: Attack Surface Reduction (ASR) | K91: CM-7 | L91: 8.9 | M91: Least-functionality win - no legitimate business use case on managed endpoints. | N91: mapped | O91: exact
A92: Baseline - Windows AI - Turn Off Copilot in Windows (User) | B92: 10_Privacy_and_AI_Data_Governance | C92: Baseline - Windows AI - Turn Off Copilot in Windows (User) | D92: settings_catalog_policy | E92: 106 | F92: Baseline - Windows AI - Turn Off Copilot in Windows (User) | G92: Windows 11 | H92: L1 | I92: Windows AI / Modern Workplace | J92: AI & Data Governance | K92: CM-7 | L92: 8.9 | M92: Cross-listed in both Windows AI and Modern Workplace source folders. Default-restrictive with per-customer override. | N92: mapped | O92: whitespace
A93: Baseline - Windows AI - Block Microsoft Recall | B93: 10_Privacy_and_AI_Data_Governance | C93: Baseline - Windows AI - Block Microsoft Recall | D93: settings_catalog_policy | E93: 105 | F93: Baseline - Windows AI - Block Microsoft Recall | G93: Windows 11 | H93: L1 | I93: Windows AI | J93: AI & Data Governance | K93: SI-3, CM-7 | L93: 8.9 | M93: High auditor/privacy visibility given Recall's screenshot-history model. Two near-identical exports exist upstream - the shorter filename is the one packaged here; confirm before deploying. | N93: mapped | O93: exact
A94: Baseline - Windows AI - Copilot access to Microsoft Edge page content for Entra account | B94: 10_Privacy_and_AI_Data_Governance | C94: Baseline - Windows AI - Copilot access to Microsoft Edge page content for Entra account | D94: settings_catalog_policy | E94: 108 | F94: Baseline - Windows AI - Copilot access to Microsoft Edge page content for Entra account | G94: Edge | H94: L2 | I94: Windows AI | J94: AI & Data Governance | K94: AC-4, CM-7 | L94: 8.9 | M94: Governs whether Copilot can read page content tied to a work identity - key DLP control as Copilot rolls out. | N94: mapped | O94: exact
A95: Baseline - Windows AI - Disable Click To Do | B95: 10_Privacy_and_AI_Data_Governance | C95: Baseline - Windows AI - Disable Click To Do | D95: settings_catalog_policy | E95: 107 | F95: Baseline - Windows AI - Disable Click To Do | G95: Windows 11 | H95: L2 | I95: Windows AI | J95: AI & Data Governance | K95: SI-3, CM-7 | L95: 8.9 | M95: Recall-adjacent on-screen OCR/action feature - same data-governance rationale as Recall. | N95: mapped | O95: exact
A96: Baseline - Windows AI - Enable Edge GenAI local foundational model | B96: 10_Privacy_and_AI_Data_Governance | C96: Baseline - Windows AI - Enable Edge GenAI local foundational model | D96: settings_catalog_policy | E96: 109 | F96: Baseline - Windows AI - Enable Edge GenAI local foundational model | G96: Edge | H96: L2 | I96: Browser Benchmarks | J96: AI & Data Governance | K96: CM-7 | L96: 8.9 | M96: On-device model - data does not leave the endpoint, but the feature is immature. Pilot before wide deployment. | N96: mapped | O96: whitespace
A97: Baseline - Windows AI - Settings Agent | B97: 10_Privacy_and_AI_Data_Governance | C97: Baseline - Windows AI - Settings Agent | D97: settings_catalog_policy | N97: UNMAPPED — no workbook row | O97: unmapped
A98: CISv4 - WIN - L2 - Disable Advertising ID | B98: 10_Privacy_and_AI_Data_Governance | C98: CISv4 - WIN - L2 - Disable Advertising ID | D98: settings_catalog_policy | E98: 72 | F98: CISv4 - WIN - L2 - Disable Advertising ID | G98: Windows 11 | H98: L2 | I98: CIS | J98: Privacy & Data Governance | K98: CM-7 | L98: 8.9 | M98: Kills the per-user advertising identifier — no functional impact, strong privacy compliance signal for ISO 8.9 | N98: mapped | O98: exact
A99: CISv4 - WIN - L2 - Upload User Activities | B99: 10_Privacy_and_AI_Data_Governance | C99: CISv4 - WIN - L2 - Upload User Activities | D99: settings_catalog_policy | E99: 73 | F99: CISv4 - WIN - L2 - Upload User Activities | G99: Windows 11 | H99: L2 | I99: CIS | J99: Privacy & Data Governance | K99: CM-7 | L99: 8.9 | M99: Disables Windows timeline syncing to Microsoft — invisible to users, prevents personal activity data leaving managed environment | N99: mapped | O99: exact
A100: CISv3 - EDGE - L1 - Allow Basic authentication for HTTP | B100: 11_Microsoft_Edge_CIS_Benchmark | C100: CISv3 - EDGE - L1 - Allow Basic authentication for HTTP | D100: settings_catalog_policy | N100: UNMAPPED — no workbook row | O100: unmapped
A101: CISv3 - EDGE - L1 - Allow Google Cast to connect to Cast devices on all IP addresses | B101: 11_Microsoft_Edge_CIS_Benchmark | C101: CISv3 - EDGE - L1 - Allow Google Cast to connect to Cast devices on all IP addresses | D101: settings_catalog_policy | E101: 127 | F101: CISv3 - EDGE - L1 - Allow Google Cast to connect to Cast devices on all IP addresses | G101: Edge | H101: L1 | I101: CIS | J101: Network Security | K101: SC-7 | L101: 8.20 | M101: Restricted to local subnet rather than any IP. | N101: mapped | O101: exact
A102: CISv3 - EDGE - L1 - Allow cross-origin HTTP Authentication prompts | B102: 11_Microsoft_Edge_CIS_Benchmark | C102: CISv3 - EDGE - L1 - Allow cross-origin HTTP Authentication prompts | D102: settings_catalog_policy | E102: 112 | F102: CISv3 - EDGE - L1 - Allow cross-origin HTTP Authentication prompts | G102: Edge | H102: L1 | I102: CIS | J102: Edge Browser Security | K102: IA-5, SC-8 | L102: 8.5 | M102: Prevents a classic cross-origin credential-phishing vector. | N102: mapped | O102: exact
A103: CISv3 - EDGE - L1 - Allow download restrictions | B103: 11_Microsoft_Edge_CIS_Benchmark | C103: CISv3 - EDGE - L1 - Allow download restrictions | D103: settings_catalog_policy | E103: 113 | F103: CISv3 - EDGE - L1 - Allow download restrictions | G103: Edge | H103: L1 | I103: CIS | J103: Edge Browser Security | K103: SI-3 | L103: 8.7 | M103: Enables dangerous-file download blocking. | N103: mapped | O103: exact
...

Sheet Control Coverage
A1: Framework | B1: Control | C1: Policies mapped | D1: Control domains covered
A2: ISO/IEC 27001:2022 | B2: 8.7 | C2: =COUNTIFS('Policy x Control'!A:A,A2,'Policy x Control'!B:B,B2) -> 65 | D2: Attack Surface Reduction (ASR), Browser Security (Chrome), Edge Browser Security, Linux Endpoint Security, Malware Protection, Privacy & Data Governance, Removable Media & USB
A3: ISO/IEC 27001:2022 | B3: 8.9 | C3: =COUNTIFS('Policy x Control'!A:A,A3,'Policy x Control'!B:B,B3) -> 39 | D3: AI & Data Governance, Attack Surface Reduction (ASR), Browser Security (Chrome), Edge Browser Security, Identity & Account Control, Linux Endpoint Security, Malware Protection, Network Security, Privacy & Data Governance, Removable Media & USB, UAC & Privileged Access
A4: ISO/IEC 27001:2022 | B4: 8.5 | C4: =COUNTIFS('Policy x Control'!A:A,A4,'Policy x Control'!B:B,B4) -> 23 | D4: Authentication & Account Security, Browser Security (Chrome), Credential Protection, Edge Browser Security, Identity & Account Control, Network Security, Passwordless Authentication, Remote Access
A5: ISO/IEC 27001:2022 | B5: 8.20 | C5: =COUNTIFS('Policy x Control'!A:A,A5,'Policy x Control'!B:B,B5) -> 21 | D5: Edge Browser Security, Firewall, Network Security, Privacy & Data Governance, Remote Access
A6: ISO/IEC 27001:2022 | B6: 8.8 | C6: =COUNTIFS('Policy x Control'!A:A,A6,'Policy x Control'!B:B,B6) -> 17 | D6: Linux Endpoint Security, Malware Protection, Patch Management
A7: ISO/IEC 27001:2022 | B7: 8.15 | C7: =COUNTIFS('Policy x Control'!A:A,A7,'Policy x Control'!B:B,B7) -> 10 | D7: Audit & Logging
A8: ISO/IEC 27001:2022 | B8: 8.1 | C8: =COUNTIFS('Policy x Control'!A:A,A8,'Policy x Control'!B:B,B8) -> 8 | D8: Authentication & Account Security, Credential Protection, Identity & Account Control, Remote Access, Screen Lock & Session
A9: ISO/IEC 27001:2022 | B9: 8.2 | C9: =COUNTIFS('Policy x Control'!A:A,A9,'Policy x Control'!B:B,B9) -> 8 | D9: Authentication & Account Security, UAC & Privileged Access
A10: ISO/IEC 27001:2022 | B10: 8.24 | C10: =COUNTIFS('Policy x Control'!A:A,A10,'Policy x Control'!B:B,B10) -> 7 | D10: Edge Browser Security, Encryption at Rest, Network Security, Privacy & Data Governance
A11: ISO/IEC 27001:2022 | B11: 5.16 | C11: =COUNTIFS('Policy x Control'!A:A,A11,'Policy x Control'!B:B,B11) -> 5 | D11: Authentication & Account Security, Identity & Account Control
A12: ISO/IEC 27001:2022 | B12: 5.17 | C12: =COUNTIFS('Policy x Control'!A:A,A12,'Policy x Control'!B:B,B12) -> 4 | D12: Authentication & Account Security, Credential Protection
A13: ISO/IEC 27001:2022 | B13: 8.13 | C13: =COUNTIFS('Policy x Control'!A:A,A13,'Policy x Control'!B:B,B13) -> 2 | D13: Resilience & Recovery
... A48: NIST SP 800-53 Rev 5 | B48: SC-13 | C48: =COUNTIFS('Policy x Control'!A:A,A48,'Policy x Control'!B:B,B48) -> 1 | D48: Network Security

Sheet Policy x Control
A1: Framework | B1: Control | C1: Policy file | D1: Category | E1: Control domain | F1: CIS level | G1: Platform | H1: Mapping status
A2: ISO/IEC 27001:2022 | B2: (no workbook row) | C2: Baseline - Device Control | D2: 08_Removable_Media_and_Device_Control | H2: UNMAPPED — no workbook row
A3: ISO/IEC 27001:2022 | B3: (no workbook row) | C3: Baseline - Linux - Device Encryption | D3: 06_Data_Encryption | H3: UNMAPPED — no workbook row
A4: ISO/IEC 27001:2022 | B4: (no workbook row) | C4: Baseline - MDE Device Tag | D4: 01_Defender_for_Endpoint (Windows + Linux) | H4: UNMAPPED — no workbook row
A5: ISO/IEC 27001:2022 | B5: (no workbook row) | C5: Baseline - Smartscreen Enhanced Phishing Protection Block Mode | D5: 01_Defender_for_Endpoint (Windows + Linux) | H5: UNMAPPED — no workbook row
A6: ISO/IEC 27001:2022 | B6: (no workbook row) | C6: Baseline - Teams - Restrict sign in to Teams to accounts in specific tenants | D6: 05_Tenant_and_Account_Access_Control | H6: UNMAPPED — no workbook row
A7: ISO/IEC 27001:2022 | B7: (no workbook row) | C7: Baseline - WHFB Muti-Factor unlock Template config | D7: 12_Passwordless_Authentication | H7: UNMAPPED — no workbook row
A8: ISO/IEC 27001:2022 | B8: (no workbook row) | C8: Baseline - Windows - Firewall | D8: 07_Firewall_and_Network_Security | H8: UNMAPPED — no workbook row
A9: ISO/IEC 27001:2022 | B9: (no workbook row) | C9: Baseline - Windows AI - Settings Agent | D9: 10_Privacy_and_AI_Data_Governance | H9: UNMAPPED — no workbook row
A10: ISO/IEC 27001:2022 | B10: (no workbook row) | C10: Baseline - Windows health monitoring | D10: 14_Modern_Workplace_and_Resilience | H10: UNMAPPED — no workbook row
A11: ISO/IEC 27001:2022 | B11: (no workbook row) | C11: CISv3 - EDGE - L1 - Allow Basic authentication for HTTP | D11: 11_Microsoft_Edge_CIS_Benchmark | H11: UNMAPPED — no workbook row
A12: ISO/IEC 27001:2022 | B12: (no workbook row) | C12: CISv3 - EDGE - L1 - Allow importing of saved passwords | D12: 11_Microsoft_Edge_CIS_Benchmark | H12: UNMAPPED — no workbook row
A13: ISO/IEC 27001:2022 | B13: (no workbook row) | C13: CISv3 - EDGE - L1 - Enable Microsoft Defender SmartScreen DNS requests | D13: 11_Microsoft_Edge_CIS_Benchmark | H13: UNMAPPED — no workbook row
... A25: ISO/IEC 27001:2022 | B25: (no workbook row) | C25: Windows-Server-ASR-Block-Credential-Stealing-LSASS | D25: 15_Defender_for_Endpoint_Windows_Server | H25: UNMAPPED — no workbook row
A26: ISO/IEC 27001:2022 | B26: (none recorded) | C26: CISv3 - EDGE - L1 - Clear browsing data when Microsoft Edge closes | D26: 11_Microsoft_Edge_CIS_Benchmark | E26: Privacy & Data Governance | F26: L1 | G26: Edge | H26: mapped
A27: ISO/IEC 27001:2022 | B27: (none recorded) | C27: CISv3 - EDGE - L1 - Clear cached images and files when Microsoft Edge closes | D27: 11_Microsoft_Edge_CIS_Benchmark | E27: Privacy & Data Governance | F27: L1 | G27: Edge | H27: mapped
A28: ISO/IEC 27001:2022 | B28: (none recorded) | C28: CISv3 - EDGE - L1 - Clear history for IE and IE mode every time you exit | D28: 11_Microsoft_Edge_CIS_Benchmark | E28: Privacy & Data Governance | F28: L1 | G28: Edge | H28: mapped
A29: ISO/IEC 27001:2022 | B29: (none recorded) | C29: CISv3 - EDGE - L1 - Configure InPrivate mode availability | D29: 11_Microsoft_Edge_CIS_Benchmark | E29: Privacy & Data Governance | F29: L1 | G29: Edge | H29: mapped
A30: ISO/IEC 27001:2022 | B30: (none recorded) | C30: CISv3 - EDGE - L1 - Configure the list of types that are excluded from synchronization | D30: 11_Microsoft_Edge_CIS_Benchmark | E30: Privacy & Data Governance | F30: L2 | G30: Edge | H30: mapped
A31: ISO/IEC 27001:2022 | B31: (none recorded) | C31: CISv3 - EDGE - L1 - Enable globally scoped HTTP auth cache | D31: 11_Microsoft_Edge_CIS_Benchmark | E31: Credential Protection | F31: L1 | G31: Edge | H31: mapped
A32: ISO/IEC 27001:2022 | B32: (none recorded) | C32: CISv3 - EDGE - L1 - In-app support Enabled | D32: 11_Microsoft_Edge_CIS_Benchmark | E32: Privacy & Data Governance | F32: L1 | G32: Edge | H32: mapped
A33: ISO/IEC 27001:2022 | B33: (none recorded) | C33: CISv3 - EDGE - L1 - Suggest similar pages when a webpage can#U2019t be found | D33: 11_Microsoft_Edge_CIS_Benchmark | E33: Privacy & Data Governance | F33: L1 | G33: Edge | H33: mapped
A34: ISO/IEC 27001:2022 | B34: (none recorded) | C34: CISv3 - EDGE - L2 - Allow file selection dialogs | D34: 11_Microsoft_Edge_CIS_Benchmark | E34: Privacy & Data Governance | F34: L2 | G34: Edge | H34: mapped
A35: ISO/IEC 27001:2022 | B35: (none recorded) | C35: CISv3 - EDGE - L2 - Configure Speech Recognition | D35: 11_Microsoft_Edge_CIS_Benchmark | E35: AI & Data Governance | F35: L2 | G35: Edge | H35: mapped
A36: ISO/IEC 27001:2022 | B36: (none recorded) | C36: CISv3 - EDGE - L2 - Default sensors setting | D36: 11_Microsoft_Edge_CIS_Benchmark | E36: Privacy & Data Governance | F36: L2 | G36: Edge | H36: mapped
A37: ISO/IEC 27001:2022 | B37: (none recorded) | C37: CISv3 - EDGE - L2 - Default setting for third-party storage partitioning | D37: 11_Microsoft_Edge_CIS_Benchmark | E37: Privacy & Data Governance | F37: L2 | G37: Edge | H37: mapped
... A254: ISO/IEC 27001:2022 | B254: 8.9 | C254: netfilter | D254: 16_Defender_for_Endpoint_macOS | E254: Network Security | F254: N/A | G254: macOS | H254: mapped
A255: NIST SP 800-53 Rev 5 | B255: (no workbook row) | C255: Baseline - Device Control | D255: 08_Removable_Media_and_Device_Control | H255: UNMAPPED — no workbook row
A256: NIST SP 800-53 Rev 5 | B256: (no workbook row) | C256: Baseline - Linux - Device Encryption | D256: 06_Data_Encryption | H256: UNMAPPED — no workbook row
A257: NIST SP 800-53 Rev 5 | B257: (no workbook row) | C257: Baseline - MDE Device Tag | D257: 01_Defender_for_Endpoint (Windows + Linux) | H257: UNMAPPED — no workbook row
A258: NIST SP 800-53 Rev 5 | B258: (no workbook row) | C258: Baseline - Smartscreen Enhanced Phishing Protection Block Mode | D258: 01_Defender_for_Endpoint (Windows + Linux) | H258: UNMAPPED — no workbook row
A259: NIST SP 800-53 Rev 5 | B259: (no workbook row) | C259: Baseline - Teams - Restrict sign in to Teams to accounts in specific tenants | D259: 05_Tenant_and_Account_Access_Control | H259: UNMAPPED — no workbook row
A260: NIST SP 800-53 Rev 5 | B260: (no workbook row) | C260: Baseline - WHFB Muti-Factor unlock Template config | D260: 12_Passwordless_Authentication | H260: UNMAPPED — no workbook row
A261: NIST SP 800-53 Rev 5 | B261: (no workbook row) | C261: Baseline - Windows - Firewall | D261: 07_Firewall_and_Network_Security | H261: UNMAPPED — no workbook row
A262: NIST SP 800-53 Rev 5 | B262: (no workbook row) | C262: Baseline - Windows AI - Settings Agent | D262: 10_Privacy_and_AI_Data_Governance | H262: UNMAPPED — no workbook row
A263: NIST SP 800-53 Rev 5 | B263: (no workbook row) | C263: Baseline - Windows health monitoring | D263: 14_Modern_Workplace_and_Resilience | H263: UNMAPPED — no workbook row
A264: NIST SP 800-53 Rev 5 | B264: (no workbook row) | C264: CISv3 - EDGE - L1 - Allow Basic authentication for HTTP | D264: 11_Microsoft_Edge_CIS_Benchmark | H264: UNMAPPED — no workbook row
A265: NIST SP 800-53 Rev 5 | B265: (no workbook row) | C265: CISv3 - EDGE - L1 - Allow importing of saved passwords | D265: 11_Microsoft_Edge_CIS_Benchmark | H265: UNMAPPED — no workbook row
A266: NIST SP 800-53 Rev 5 | B266: (no workbook row) | C266: CISv3 - EDGE - L1 - Enable Microsoft Defender SmartScreen DNS requests | D266: 11_Microsoft_Edge_CIS_Benchmark | H266: UNMAPPED — no workbook row
... A278: NIST SP 800-53 Rev 5 | B278: (no workbook row) | C278: Windows-Server-ASR-Block-Credential-Stealing-LSASS | D278: 15_Defender_for_Endpoint_Windows_Server | H278: UNMAPPED — no workbook row
A279: NIST SP 800-53 Rev 5 | B279: (none recorded) | C279: CISv3 - EDGE - L1 - Clear browsing data when Microsoft Edge closes | D279: 11_Microsoft_Edge_CIS_Benchmark | E279: Privacy & Data Governance | F279: L1 | G279: Edge | H279: mapped
A280: NIST SP 800-53 Rev 5 | B280: (none recorded) | C280: CISv3 - EDGE - L1 - Clear cached images and files when Microsoft Edge closes | D280: 11_Microsoft_Edge_CIS_Benchmark | E280: Privacy & Data Governance | F280: L1 | G280: Edge | H280: mapped
A281: NIST SP 800-53 Rev 5 | B281: (none recorded) | C281: CISv3 - EDGE - L1 - Clear history for IE and IE mode every time you exit | D281: 11_Microsoft_Edge_CIS_Benchmark | E281: Privacy & Data Governance | F281: L1 | G281: Edge | H281: mapped
A282: NIST SP 800-53 Rev 5 | B282: (none recorded) | C282: CISv3 - EDGE - L1 - Configure InPrivate mode availability | D282: 11_Microsoft_Edge_CIS_Benchmark | E282: Privacy & Data Governance | F282: L1 | G282: Edge | H282: mapped
A283: NIST SP 800-53 Rev 5 | B283: (none recorded) | C283: CISv3 - EDGE - L1 - Configure the list of types that are excluded from synchronization | D283: 11_Microsoft_Edge_CIS_Benchmark | E283: Privacy & Data Governance | F283: L2 | G283: Edge | H283: mapped
A284: NIST SP 800-53 Rev 5 | B284: (none recorded) | C284: CISv3 - EDGE - L1 - Enable globally scoped HTTP auth cache | D284: 11_Microsoft_Edge_CIS_Benchmark | E284: Credential Protection | F284: L1 | G284: Edge | H284: mapped
A285: NIST SP 800-53 Rev 5 | B285: (none recorded) | C285: CISv3 - EDGE - L1 - In-app support Enabled | D285: 11_Microsoft_Edge_CIS_Benchmark | E285: Privacy & Data Governance | F285: L1 | G285: Edge | H285: mapped
A286: NIST SP 800-53 Rev 5 | B286: (none recorded) | C286: CISv3 - EDGE - L1 - Suggest similar pages when a webpage can#U2019t be found | D286: 11_Microsoft_Edge_CIS_Benchmark | E286: Privacy & Data Governance | F286: L1 | G286: Edge | H286: mapped
A287: NIST SP 800-53 Rev 5 | B287: (none recorded) | C287: CISv3 - EDGE - L2 - Allow file selection dialogs | D287: 11_Microsoft_Edge_CIS_Benchmark | E287: Privacy & Data Governance | F287: L2 | G287: Edge | H287: mapped
A288: NIST SP 800-53 Rev 5 | B288: (none recorded) | C288: CISv3 - EDGE - L2 - Configure Speech Recognition | D288: 11_Microsoft_Edge_CIS_Benchmark | E288: AI & Data Governance | F288: L2 | G288: Edge | H288: mapped
A289: NIST SP 800-53 Rev 5 | B289: (none recorded) | C289: CISv3 - EDGE - L2 - Default sensors setting | D289: 11_Microsoft_Edge_CIS_Benchmark | E289: Privacy & Data Governance | F289: L2 | G289: Edge | H289: mapped
A290: NIST SP 800-53 Rev 5 | B290: (none recorded) | C290: CISv3 - EDGE - L2 - Default setting for third-party storage partitioning | D290: 11_Microsoft_Edge_CIS_Benchmark | E290: Privacy & Data Governance | F290: L2 | G290: Edge | H290: mapped
... A576: NIST SP 800-53 Rev 5 | B576: SI-7 | C576: notif | D576: 16_Defender_for_Endpoint_macOS | E576: Malware Protection | F576: N/A | G576: macOS | H576: mapped

Sheet Unmapped Gap
A1: The 24 policies with no framework mapping
A2: These deploy correctly — the gap is documentation, not configuration. Their rows in CIS_Compliance_Baseline_v2.xlsx are numbered but entirely blank, so no mapping exists to recover. Fill the three yellow columns in, then re-run the mapping to fold them into the coverage figures.
A4: Blank workbook rows: 11, 21, 24, 25, 33, 38, 43, 49, 52, 55, 60, 75, 78, 89, 91, 92, 97, 99, 103, 110, 117, 183, 189, 196
A6: Policy file | B6: Category | C6: Graph object shape | D6: Control domain — TO FILL | E6: NIST SP 800-53 Rev 5 — TO FILL | F6: ISO/IEC 27001:2022 — TO FILL
A7: Baseline - MDE Device Tag | B7: 01_Defender_for_Endpoint (Windows + Linux) | C7: legacy_device_configuration
A8: Baseline - Smartscreen Enhanced Phishing Protection Block Mode | B8: 01_Defender_for_Endpoint (Windows + Linux) | C8: settings_catalog_policy
A9: CISv4 - WIN - L1 - ASR Block executable files from running unless they meet a prevalence, age, or trusted list criterion' | B9: 01_Defender_for_Endpoint (Windows + Linux) | C9: settings_catalog_policy
A10: CISv4 - WIN - L1 - ASR Block execution of potentially obfuscated scripts | B10: 01_Defender_for_Endpoint (Windows + Linux) | C10: settings_catalog_policy
A11: CISv4 - WIN - L1 - Allow Basic authentication WinRM Client | B11: 02_Windows_CIS_Benchmark_Hardening | C11: settings_catalog_policy
A12: CISv4 - WIN - L1 - Allow Indexing Encrypted Stores Or Items | B12: 02_Windows_CIS_Benchmark_Hardening | C12: settings_catalog_policy
A13: CISv4 - WIN - L1 - Credential Guard | B13: 02_Windows_CIS_Benchmark_Hardening | C13: settings_catalog_policy
A14: CISv4 - WIN - L1 - MSS (AutoAdminLogon) Enable Automatic Logon (not recommended) | B14: 02_Windows_CIS_Benchmark_Hardening | C14: settings_catalog_policy
A15: CISv4 - WIN - L1 - Microsoft network server Digitally sign communications (always) | B15: 02_Windows_CIS_Benchmark_Hardening | C15: settings_catalog_policy
A16: CISv4 - WIN - L1 - Audit Special Logon | B16: 03_Audit_and_Logging | C16: settings_catalog_policy
A17: Baseline - Teams - Restrict sign in to Teams to accounts in specific tenants | B17: 05_Tenant_and_Account_Access_Control | C17: settings_catalog_policy
A18: Baseline - Linux - Device Encryption | B18: 06_Data_Encryption | C18: compliance_policy
... A30: Windows-Server-ASR-Block-Credential-Stealing-LSASS | B30: 15_Defender_for_Endpoint_Windows_Server | C30: settings_catalog_policy
A32: Example of the expected format (delete this row before use):
A33: CISv4 - WIN - L1 - Credential Guard | B33: 02_Windows_CIS_Benchmark_Hardening | C33: settings_catalog_policy | D33: Credential Protection | E33: SC-3, SI-16 | F33: 8.1, 8.5

Sheet Read Me
A1: Read me — provenance and method
A3: What this is | B3: A factual mapping of each of the 222 Intune policies in this baseline to its NIST SP 800-53 Rev 5 controls and ISO/IEC 27001:2022 Annex A clauses.
A5: Sources | B5: Framework values: CIS_Compliance_Baseline_v2.xlsx, ‘Compliance Baseline’ sheet. Policy list, categories, Graph object shapes and deployed names: Intune-Baseline/manifest.json, generated from the 222 files in source-pack/.
A7: Nothing is inferred | B7: Every NIST and ISO value is copied verbatim from the workbook. Where the workbook holds no data, the cells are blank and the policy is marked UNMAPPED. No control was guessed, derived from a policy's name, or filled in by analogy — that would manufacture audit evidence.
A9: How rows were matched | B9: The workbook keys on policy name; the pack keys on filename, and the two have drifted. Matching ran a ladder from strictest to loosest: exact string, then whitespace, then punctuation, then rule-name prefix. Every policy resolved deterministically to exactly one workbook row — no workbook row was used twice, and no similarity/fuzzy matching survived into this output. The method used is recorded per row.
A11: What ‘UNMAPPED’ means | B11: The policy deploys correctly. Only its framework documentation is missing, because its workbook row is blank. See the Unmapped Gap tab.
A13: Two placeholders | B13: On the Policy x Control tab: ‘(no workbook row)’ = the 24 unmapped policies. ‘(none recorded)’ = the workbook row exists but records a literal ‘-’ instead of a control (15 Edge rows). Neither means ‘no control applies’; both mean ‘nothing was written down’.
A15: Counts recalculate | B15: Figures on Summary and Control Coverage are formulas over the data tabs, not typed-in numbers. Fill in the Unmapped Gap tab and re-run the mapping, and the coverage figures move with it.
A17: Known discrepancy | B17: “Configure the list of types that are excluded from synchronization” is recorded as L2 in the workbook but the policy file is named CISv3 - EDGE - L1. One of the two is wrong; this workbook reports the workbook's value.
A19: Generated | B19: 2026-09-09, from the source pack shipped in Intune-Baseline-Toolkit-v2.zip.
